{"MatchScores": [{"matchLevel": "QUALIFICATION", "matchSeries": 0, "matchNumber": 1, "randomization": 2, "alliances": [{"alliance": "Blue", "team": 0, "sideOfField": "SCORING_SIDE", "initSignalSleeve1": true, "initSignalSleeve2": false, "robot1Auto": "SIGNAL_ZONE", "robot2Auto": "NONE", "autoTerminal": 1, "autoJunctions": [[[], [], [], [], []], [[], [], [], [], []], [[], [], [], [], []], [[], [], [], [], []], [[], [], [], [], []]], "dcJunctions": [[["OTHER_CONE"], [], [], [], ["MY_CONE"]], [[], ["OTHER_CONE"], [], [], []], [["MY_CONE"], [], ["OTHER_CONE"], [], []], [[], [], [], ["OTHER_CONE"], []], [["MY_CONE"], [], ["MY_CONE"], [], ["OTHER_CONE"]]], "dcTerminalNear": 5, "dcTerminalFar": 0, "egNavigated1": false, "egNavigated2": true, "minorPenalties": 1, "majorPenalties": 0, "autoNavigationPoints": 0, "signalBonusPoints": 20, "autoJunctionConePoints": 0, "autoTerminalConePoints": 1, "dcJunctionConePoints": 8, "dcTerminalConePoints": 5, "ownershipPoints": 12, "circuitPoints": 0, "egNavigationPoints": 2, "autoPoints": 21, "dcPoints": 13, "endgamePoints": 14, "penaltyPointsCommitted": 10, "prePenaltyTotal": 48, "autoJunctionCones": [0, 0, 0, 0], "dcJunctionCones": [4, 0, 0, 0], "beacons": 0, "ownedJunctions": 4, "circuit": false, "totalPoints": 68}, {"alliance": "Red", "team": 0, "sideOfField": "SCORING_SIDE", "initSignalSleeve1": false, "initSignalSleeve2": false, "robot1Auto": "NONE", "robot2Auto": "NONE", "autoTerminal": 0, "autoJunctions": [[[], [], [], [], []], [[], [], [], [], []], [[], [], [], [], []], [[], [], [], [], []], [[], [], [], [], []]], "dcJunctions": [[["MY_CONE"], [], [], [], ["OTHER_CONE"]], [[], ["MY_CONE"], [], [], []], [["OTHER_CONE"], [], ["MY_CONE"], [], []], [[], [], [], ["MY_CONE"], []], [["OTHER_CONE"], [], ["OTHER_CONE"], [], ["MY_CONE"]]], "dcTerminalNear": 1, "dcTerminalFar": 1, "egNavigated1": true, "egNavigated2": false, "minorPenalties": 2, "majorPenalties": 0, "autoNavigationPoints": 0, "signalBonusPoints": 0, "autoJunctionConePoints": 0, "autoTerminalConePoints": 0, "dcJunctionConePoints": 14, "dcTerminalConePoints": 2, "ownershipPoints": 15, "circuitPoints": 20, "egNavigationPoints": 2, "autoPoints": 0, "dcPoints": 16, "endgamePoints": 37, "penaltyPointsCommitted": 20, "prePenaltyTotal": 53, "autoJunctionCones": [0, 0, 0, 0], "dcJunctionCones": [3, 0, 2, 0], "beacons": 0, "ownedJunctions": 5, "circuit": true, "totalPoints": 63}]}, {"matchLevel": "QUALIFICATION", "matchSeries": 0, "matchNumber": 2, "randomization": 3, "alliances": [{"alliance": "Blue", "team": 0, "sideOfField": "SCORING_SIDE", "initSignalSleeve1": false, "initSignalSleeve2": false, "robot1Auto": "SUBSTATION_TERMINAL", "robot2Auto": "NONE", "autoTerminal": 0, "autoJunctions": [[[], [], [], [], []], [[], [], [], [], []], [[], [], [], [], []], [[], [], [], [], []], [[], [], [], [], []]], "dcJunctions": [[["OTHER_CONE"], [], ["OTHER_CONE"], [], ["OTHER_CONE"]], [[], ["MY_CONE"], [], [], []], [[], ["MY_CONE"], ["OTHER_CONE"], [], []], [["MY_CONE"], [], [], [], []], [["OTHER_CONE"], [], ["OTHER_CONE"], [], []]], "dcTerminalNear": 1, "dcTerminalFar": 0, "egNavigated1": true, "egNavigated2": false, "minorPenalties": 0, "majorPenalties": 0, "autoNavigationPoints": 2, "signalBonusPoints": 0, "autoJunctionConePoints": 0, "autoTerminalConePoints": 0, "dcJunctionConePoints": 12, "dcTerminalConePoints": 1, "ownershipPoints": 9, "circuitPoints": 0, "egNavigationPoints": 2, "autoPoints": 2, "dcPoints": 13, "endgamePoints": 11, "penaltyPointsCommitted": 0, "prePenaltyTotal": 26, "autoJunctionCones": [0, 0, 0, 0], "dcJunctionCones": [0, 1, 1, 1], "beacons": 0, "ownedJunctions": 3, "circuit": false, "totalPoints": 26}, {"alliance": "Red", "team": 0, "sideOfField": "SCORING_SIDE", "initSignalSleeve1": true, "initSignalSleeve2": false, "robot1Auto": "SIGNAL_ZONE", "robot2Auto": "NONE", "autoTerminal": 1, "autoJunctions": [[[], [], [], [], []], [[], [], [], [], []], [[], [], [], [], []], [[], [], [], [], []], [[], [], [], [], []]], "dcJunctions": [[["MY_CONE"], [], ["MY_CONE"], [], ["MY_CONE"]], [[], ["OTHER_CONE"], [], [], []], [[], ["OTHER_CONE"], ["MY_CONE"], [], []], [["OTHER_CONE"], [], [], [], []], [["MY_CONE"], [], ["MY_CONE"], [], []]], "dcTerminalNear": 4, "dcTerminalFar": 0, "egNavigated1": true, "egNavigated2": false, "minorPenalties": 0, "majorPenalties": 0, "autoNavigationPoints": 0, "signalBonusPoints": 20, "autoJunctionConePoints": 0, "autoTerminalConePoints": 1, "dcJunctionConePoints": 12, "dcTerminalConePoints": 4, "ownershipPoints": 18, "circuitPoints": 0, "egNavigationPoints": 2, "autoPoints": 21, "dcPoints": 16, "endgamePoints": 20, "penaltyPointsCommitted": 0, "prePenaltyTotal": 57, "autoJunctionCones": [0, 0, 0, 0], "dcJunctionCones": [6, 0, 0, 0], "beacons": 0, "ownedJunctions": 6, "circuit": false, "totalPoints": 57}]}, {"matchLevel": "QUALIFICATION", "matchSeries": 0, "matchNumber": 3, "randomization": 2, "alliances": [{"alliance": "Blue", "team": 0, "sideOfField": "SCORING_SIDE", "initSignalSleeve1": false, "initSignalSleeve2": false, "robot1Auto": "NONE", "robot2Auto": "NONE", "autoTerminal": 0, "autoJunctions": [[[], [], [], [], []], [[], [], [], [], []], [[], [], [], [], []], [[], [], [], [], []], [[], [], [], [], []]], "dcJunctions": [[["MY_CONE"], [], [], [], []], [[], [], [], [], []], [[], [], ["MY_CONE"], [], []], [[], [], [], ["MY_CONE"], ["MY_CONE"]], [[], [], [], [], []]], "dcTerminalNear": 4, "dcTerminalFar": 0, "egNavigated1": true, "egNavigated2": false, "minorPenalties": 4, "majorPenalties": 0, "autoNavigationPoints": 0, "signalBonusPoints": 0, "autoJunctionConePoints": 0, "autoTerminalConePoints": 0, "dcJunctionConePoints": 11, "dcTerminalConePoints": 4, "ownershipPoints": 12, "circuitPoints": 0, "egNavigationPoints": 2, "autoPoints": 0, "dcPoints": 15, "endgamePoints": 14, "penaltyPointsCommitted": 40, "prePenaltyTotal": 29, "autoJunctionCones": [0, 0, 0, 0], "dcJunctionCones": [2, 1, 1, 0], "beacons": 0, "ownedJunctions": 4, "circuit": false, "totalPoints": 39}, {"alliance": "Red", "team": 0, "sideOfField": "SCORING_SIDE", "initSignalSleeve1": false, "initSignalSleeve2": false, "robot1Auto": "NONE", "robot2Auto": "SUBSTATION_TERMINAL", "autoTerminal": 0, "autoJunctions": [[[], [], [], [], []], [[], [], [], [], []], [[], [], [], [], []], [[], [], [], [], []], [[], [], [], [], []]], "dcJunctions": [[["OTHER_CONE"], [], [], [], []], [[], [], [], [], []], [[], [], ["OTHER_CONE"], [], []], [[], [], [], ["OTHER_CONE"], ["OTHER_CONE"]], [[], [], [], [], []]], "dcTerminalNear": 3, "dcTerminalFar": 0, "egNavigated1": false, "egNavigated2": true, "minorPenalties": 1, "majorPenalties": 0, "autoNavigationPoints": 2, "signalBonusPoints": 0, "autoJunctionConePoints": 0, "autoTerminalConePoints": 0, "dcJunctionConePoints": 0, "dcTerminalConePoints": 3, "ownershipPoints": 0, "circuitPoints": 0, "egNavigationPoints": 2, "autoPoints": 2, "dcPoints": 3, "endgamePoints": 2, "penaltyPointsCommitted": 10, "prePenaltyTotal": 7, "autoJunctionCones": [0, 0, 0, 0], "dcJunctionCones": [0, 0, 0, 0], "beacons": 0, "ownedJunctions": 0, "circuit": false, "totalPoints": 47}]}, {"matchLevel": "QUALIFICATION", "matchSeries": 0, "matchNumber": 4, "randomization": 2, "alliances": [{"alliance": "Blue", "team": 0, "sideOfField": "SCORING_SIDE", "initSignalSleeve1": false, "initSignalSleeve2": false, "robot1Auto": "NONE", "robot2Auto": "NONE", "autoTerminal": 0, "autoJunctions": [[[], [], [], [], []], [[], [], [], [], []], [[], [], [], [], []], [[], [], [], [], []], [[], [], [], [], []]], "dcJunctions": [[["OTHER_CONE"], [], ["OTHER_CONE"], [], ["OTHER_CONE"]], [[], [], [], [], []], [[], [], ["OTHER_CONE"], [], []], [[], [], [], [], []], [[], [], ["OTHER_CONE"], [], []]], "dcTerminalNear": 4, "dcTerminalFar": 1, "egNavigated1": false, "egNavigated2": true, "minorPenalties": 0, "majorPenalties": 0, "autoNavigationPoints": 0, "signalBonusPoints": 0, "autoJunctionConePoints": 0, "autoTerminalConePoints": 0, "dcJunctionConePoints": 0, "dcTerminalConePoints": 5, "ownershipPoints": 0, "circuitPoints": 0, "egNavigationPoints": 2, "autoPoints": 0, "dcPoints": 5, "endgamePoints": 2, "penaltyPointsCommitted": 0, "prePenaltyTotal": 7, "autoJunctionCones": [0, 0, 0, 0], "dcJunctionCones": [0, 0, 0, 0], "beacons": 0, "ownedJunctions": 0, "circuit": false, "totalPoints": 27}, {"alliance": "Red", "team": 0, "sideOfField": "SCORING_SIDE", "initSignalSleeve1": true, "initSignalSleeve2": false, "robot1Auto": "SIGNAL_ZONE", "robot2Auto": "SUBSTATION_TERMINAL", "autoTerminal": 1, "autoJunctions": [[[], [], [], [], []], [[], [], [], [], []], [[], [], [], [], []], [[], [], [], [], []], [[], [], [], [], []]], "dcJunctions": [[["MY_CONE"], [], ["MY_CONE"], [], ["MY_CONE"]], [[], [], [], [], []], [[], [], ["MY_CONE"], [], []], [[], [], [], [], []], [[], [], ["MY_CONE"], [], []]], "dcTerminalNear": 6, "dcTerminalFar": 0, "egNavigated1": true, "egNavigated2": false, "minorPenalties": 2, "majorPenalties": 0, "autoNavigationPoints": 2, "signalBonusPoints": 20, "autoJunctionConePoints": 0, "autoTerminalConePoints": 1, "dcJunctionConePoints": 10, "dcTerminalConePoints": 6, "ownershipPoints": 15, "circuitPoints": 0, "egNavigationPoints": 2, "autoPoints": 23, "dcPoints": 16, "endgamePoints": 17, "penaltyPointsCommitted": 20, "prePenaltyTotal": 56, "autoJunctionCones": [0, 0, 0, 0], "dcJunctionCones": [5, 0, 0, 0], "beacons": 0, "ownedJunctions": 5, "circuit": false, "totalPoints": 56}]}, {"matchLevel": "QUALIFICATION", "matchSeries": 0, "matchNumber": 5, "randomization": 5, "alliances": [{"alliance": "Blue", "team": 0, "sideOfField": "SCORING_SIDE", "initSignalSleeve1": false, "initSignalSleeve2": false, "robot1Auto": "NONE", "robot2Auto": "SUBSTATION_TERMINAL", "autoTerminal": 0, "autoJunctions": [[[], [], [], [], []], [[], [], [], [], []], [[], [], [], [], []], [[], [], [], [], []], [[], [], [], [], []]], "dcJunctions": [[["OTHER_CONE", "MY_CONE"], [], [], [], []], [[], ["MY_CONE"], [], [], []], [[], ["MY_CONE", "MY_CONE", "MY_CONE"], ["OTHER_CONE"], [], []], [[], [], ["MY_CONE"], [], []], [[], [], [], [], ["OTHER_CONE"]]], "dcTerminalNear": 4, "dcTerminalFar": 0, "egNavigated1": false, "egNavigated2": true, "minorPenalties": 2, "majorPenalties": 0, "autoNavigationPoints": 2, "signalBonusPoints": 0, "autoJunctionConePoints": 0, "autoTerminalConePoints": 0, "dcJunctionConePoints": 26, "dcTerminalConePoints": 4, "ownershipPoints": 12, "circuitPoints": 0, "egNavigationPoints": 2, "autoPoints": 2, "dcPoints": 30, "endgamePoints": 14, "penaltyPointsCommitted": 20, "prePenaltyTotal": 46, "autoJunctionCones": [0, 0, 0, 0], "dcJunctionCones": [1, 0, 1, 4], "beacons": 0, "ownedJunctions": 4, "circuit": false, "totalPoints": 66}, {"alliance": "Red", "team": 0, "sideOfField": "SCORING_SIDE", "initSignalSleeve1": false, "initSignalSleeve2": true, "robot1Auto": "SUBSTATION_TERMINAL", "robot2Auto": "SIGNAL_ZONE", "autoTerminal": 1, "autoJunctions": [[[], [], [], [], []], [[], [], [], [], []], [[], [], [], [], []], [[], [], [], [], []], [[], [], [], [], []]], "dcJunctions": [[["MY_CONE", "OTHER_CONE"], [], [], [], []], [[], ["OTHER_CONE"], [], [], []], [[], ["OTHER_CONE", "OTHER_CONE", "OTHER_CONE"], ["MY_CONE"], [], []], [[], [], ["OTHER_CONE"], [], []], [[], [], [], [], ["MY_CONE"]]], "dcTerminalNear": 1, "dcTerminalFar": 0, "egNavigated1": false, "egNavigated2": true, "minorPenalties": 2, "majorPenalties": 0, "autoNavigationPoints": 2, "signalBonusPoints": 20, "autoJunctionConePoints": 0, "autoTerminalConePoints": 1, "dcJunctionConePoints": 6, "dcTerminalConePoints": 1, "ownershipPoints": 6, "circuitPoints": 0, "egNavigationPoints": 2, "autoPoints": 23, "dcPoints": 7, "endgamePoints": 8, "penaltyPointsCommitted": 20, "prePenaltyTotal": 38, "autoJunctionCones": [0, 0, 0, 0], "dcJunctionCones": [3, 0, 0, 0], "beacons": 0, "ownedJunctions": 2, "circuit": false, "totalPoints": 58}]}, {"matchLevel": "QUALIFICATION", "matchSeries": 0, "matchNumber": 6, "randomization": 4, "alliances": [{"alliance": "Blue", "team": 0, "sideOfField": "SCORING_SIDE", "initSignalSleeve1": false, "initSignalSleeve2": false, "robot1Auto": "NONE", "robot2Auto": "SUBSTATION_TERMINAL", "autoTerminal": 1, "autoJunctions": [[[], [], [], [], []], [[], [], [], [], []], [[], [], [], [], []], [[], [], [], [], []], [[], [], [], [], []]], "dcJunctions": [[[], [], [], [], []], [[], [], ["MY_CONE"], [], []], [[], ["MY_CONE"], [], [], []], [[], [], [], [], []], [[], [], [], [], []]], "dcTerminalNear": 1, "dcTerminalFar": 1, "egNavigated1": false, "egNavigated2": true, "minorPenalties": 0, "majorPenalties": 0, "autoNavigationPoints": 2, "signalBonusPoints": 0, "autoJunctionConePoints": 0, "autoTerminalConePoints": 1, "dcJunctionConePoints": 10, "dcTerminalConePoints": 2, "ownershipPoints": 6, "circuitPoints": 0, "egNavigationPoints": 2, "autoPoints": 3, "dcPoints": 12, "endgamePoints": 8, "penaltyPointsCommitted": 0, "prePenaltyTotal": 23, "autoJunctionCones": [0, 0, 0, 0], "dcJunctionCones": [0, 0, 0, 2], "beacons": 0, "ownedJunctions": 2, "circuit": false, "totalPoints": 23}, {"alliance": "Red", "team": 0, "sideOfField": "SCORING_SIDE", "initSignalSleeve1": false, "initSignalSleeve2": false, "robot1Auto": "SUBSTATION_TERMINAL", "robot2Auto": "NONE", "autoTerminal": 1, "autoJunctions": [[[], [], [], [], []], [[], [], [], [], []], [[], [], [], [], []], [[], [], [], [], []], [[], [], [], [], []]], "dcJunctions": [[[], [], [], [], []], [[], [], ["OTHER_CONE"], [], []], [[], ["OTHER_CONE"], [], [], []], [[], [], [], [], []], [[], [], [], [], []]], "dcTerminalNear": 1, "dcTerminalFar": 2, "egNavigated1": false, "egNavigated2": false, "minorPenalties": 0, "majorPenalties": 0, "autoNavigationPoints": 2, "signalBonusPoints": 0, "autoJunctionConePoints": 0, "autoTerminalConePoints": 1, "dcJunctionConePoints": 0, "dcTerminalConePoints": 3, "ownershipPoints": 0, "circuitPoints": 0, "egNavigationPoints": 0, "autoPoints": 3, "dcPoints": 3, "endgamePoints": 0, "penaltyPointsCommitted": 0, "prePenaltyTotal": 6, "autoJunctionCones": [0, 0, 0, 0], "dcJunctionCones": [0, 0, 0, 0], "beacons": 0, "ownedJunctions": 0, "circuit": false, "totalPoints": 6}]}, {"matchLevel": "QUALIFICATION", "matchSeries": 0, "matchNumber": 7, "randomization": 6, "alliances": [{"alliance": "Blue", "team": 0, "sideOfField": "SCORING_SIDE", "initSignalSleeve1": false, "initSignalSleeve2": false, "robot1Auto": "NONE", "robot2Auto": "SIGNAL_ZONE", "autoTerminal": 1, "autoJunctions": [[[], [], [], [], []], [[], [], [], [], []], [[], [], [], [], []], [[], [], [], [], []], [[], [], [], [], []]], "dcJunctions": [[["MY_CONE"], [], [], [], ["MY_CONE"]], [[], [], ["MY_CONE", "MY_CONE", "MY_CONE", "MY_CONE", "MY_CONE"], [], []], [[], ["MY_CONE", "MY_CONE", "MY_CONE"], ["MY_CONE"], [], []], [[], [], [], [], []], [["MY_CONE"], [], [], [], []]], "dcTerminalNear": 4, "dcTerminalFar": 1, "egNavigated1": false, "egNavigated2": true, "minorPenalties": 0, "majorPenalties": 0, "autoNavigationPoints": 0, "signalBonusPoints": 10, "autoJunctionConePoints": 0, "autoTerminalConePoints": 1, "dcJunctionConePoints": 48, "dcTerminalConePoints": 5, "ownershipPoints": 18, "circuitPoints": 0, "egNavigationPoints": 2, "autoPoints": 11, "dcPoints": 53, "endgamePoints": 20, "penaltyPointsCommitted": 0, "prePenaltyTotal": 84, "autoJunctionCones": [0, 0, 0, 0], "dcJunctionCones": [4, 0, 0, 8], "beacons": 0, "ownedJunctions": 6, "circuit": false, "totalPoints": 104}, {"alliance": "Red", "team": 0, "sideOfField": "SCORING_SIDE", "initSignalSleeve1": false, "initSignalSleeve2": false, "robot1Auto": "SUBSTATION_TERMINAL", "robot2Auto": "NONE", "autoTerminal": 1, "autoJunctions": [[[], [], [], [], []], [[], [], [], [], []], [[], [], [], [], []], [[], [], [], [], []], [[], [], [], [], []]], "dcJunctions": [[["OTHER_CONE"], [], [], [], ["OTHER_CONE"]], [[], [], ["OTHER_CONE", "OTHER_CONE", "OTHER_CONE", "OTHER_CONE", "OTHER_CONE"], [], []], [[], ["OTHER_CONE", "OTHER_CONE", "OTHER_CONE"], ["OTHER_CONE"], [], []], [[], [], [], [], []], [["OTHER_CONE"], [], [], [], []]], "dcTerminalNear": 8, "dcTerminalFar": 0, "egNavigated1": false, "egNavigated2": false, "minorPenalties": 2, "majorPenalties": 0, "autoNavigationPoints": 2, "signalBonusPoints": 0, "autoJunctionConePoints": 0, "autoTerminalConePoints": 1, "dcJunctionConePoints": 0, "dcTerminalConePoints": 8, "ownershipPoints": 0, "circuitPoints": 0, "egNavigationPoints": 0, "autoPoints": 3, "dcPoints": 8, "endgamePoints": 0, "penaltyPointsCommitted": 20, "prePenaltyTotal": 11, "autoJunctionCones": [0, 0, 0, 0], "dcJunctionCones": [0, 0, 0, 0], "beacons": 0, "ownedJunctions": 0, "circuit": false, "totalPoints": 11}]}, {"matchLevel": "QUALIFICATION", "matchSeries": 0, "matchNumber": 8, "randomization": 4, "alliances": [{"alliance": "Blue", "team": 0, "sideOfField": "SCORING_SIDE", "initSignalSleeve1": false, "initSignalSleeve2": true, "robot1Auto": "SUBSTATION_TERMINAL", "robot2Auto": "SIGNAL_ZONE", "autoTerminal": 1, "autoJunctions": [[[], [], [], [], []], [[], [], [], [], []], [[], [], [], [], []], [[], [], [], [], []], [[], [], [], [], []]], "dcJunctions": [[["MY_CONE"], [], ["MY_CONE"], [], ["MY_CONE"]], [[], [], ["OTHER_CONE", "OTHER_CONE", "OTHER_CONE", "OTHER_CONE"], [], []], [[], [], ["MY_CONE"], [], []], [[], [], ["OTHER_CONE", "OTHER_CONE", "OTHER_CONE", "OTHER_CONE", "OTHER_CONE"], [], []], [[], [], ["MY_CONE"], [], []]], "dcTerminalNear": 12, "dcTerminalFar": 0, "egNavigated1": true, "egNavigated2": true, "minorPenalties": 1, "majorPenalties": 0, "autoNavigationPoints": 2, "signalBonusPoints": 20, "autoJunctionConePoints": 0, "autoTerminalConePoints": 1, "dcJunctionConePoints": 10, "dcTerminalConePoints": 12, "ownershipPoints": 15, "circuitPoints": 0, "egNavigationPoints": 4, "autoPoints": 23, "dcPoints": 22, "endgamePoints": 19, "penaltyPointsCommitted": 10, "prePenaltyTotal": 64, "autoJunctionCones": [0, 0, 0, 0], "dcJunctionCones": [5, 0, 0, 0], "beacons": 0, "ownedJunctions": 5, "circuit": false, "totalPoints": 74}, {"alliance": "Red", "team": 0, "sideOfField": "SCORING_SIDE", "initSignalSleeve1": false, "initSignalSleeve2": false, "robot1Auto": "NONE", "robot2Auto": "NONE", "autoTerminal": 0, "autoJunctions": [[[], [], [], [], []], [[], [], [], [], []], [[], [], [], [], []], [[], [], [], [], []], [[], [], [], [], []]], "dcJunctions": [[["OTHER_CONE"], [], ["OTHER_CONE"], [], ["OTHER_CONE"]], [[], [], ["MY_CONE", "MY_CONE", "MY_CONE", "MY_CONE"], [], []], [[], [], ["OTHER_CONE"], [], []], [[], [], ["MY_CONE", "MY_CONE", "MY_CONE", "MY_CONE", "MY_CONE"], [], []], [[], [], ["OTHER_CONE"], [], []]], "dcTerminalNear": 3, "dcTerminalFar": 2, "egNavigated1": true, "egNavigated2": false, "minorPenalties": 1, "majorPenalties": 0, "autoNavigationPoints": 0, "signalBonusPoints": 0, "autoJunctionConePoints": 0, "autoTerminalConePoints": 0, "dcJunctionConePoints": 45, "dcTerminalConePoints": 5, "ownershipPoints": 6, "circuitPoints": 0, "egNavigationPoints": 2, "autoPoints": 0, "dcPoints": 50, "endgamePoints": 8, "penaltyPointsCommitted": 10, "prePenaltyTotal": 58, "autoJunctionCones": [0, 0, 0, 0], "dcJunctionCones": [0, 0, 0, 9], "beacons": 0, "ownedJunctions": 2, "circuit": false, "totalPoints": 68}]}, {"matchLevel": "QUALIFICATION", "matchSeries": 0, "matchNumber": 9, "randomization": 4, "alliances": [{"alliance": "Blue", "team": 0, "sideOfField": "SCORING_SIDE", "initSignalSleeve1": false, "initSignalSleeve2": false, "robot1Auto": "NONE", "robot2Auto": "SUBSTATION_TERMINAL", "autoTerminal": 1, "autoJunctions": [[[], [], [], [], []], [[], [], [], [], []], [[], [], [], [], []], [[], [], [], [], []], [[], [], [], [], []]], "dcJunctions": [[[], [], [], [], []], [[], [], [], [], []], [[], [], [], [], []], [[], [], [], [], []], [[], [], [], [], []]], "dcTerminalNear": 3, "dcTerminalFar": 1, "egNavigated1": true, "egNavigated2": false, "minorPenalties": 2, "majorPenalties": 0, "autoNavigationPoints": 2, "signalBonusPoints": 0, "autoJunctionConePoints": 0, "autoTerminalConePoints": 1, "dcJunctionConePoints": 0, "dcTerminalConePoints": 4, "ownershipPoints": 0, "circuitPoints": 0, "egNavigationPoints": 2, "autoPoints": 3, "dcPoints": 4, "endgamePoints": 2, "penaltyPointsCommitted": 20, "prePenaltyTotal": 9, "autoJunctionCones": [0, 0, 0, 0], "dcJunctionCones": [0, 0, 0, 0], "beacons": 0, "ownedJunctions": 0, "circuit": false, "totalPoints": 19}, {"alliance": "Red", "team": 0, "sideOfField": "SCORING_SIDE", "initSignalSleeve1": false, "initSignalSleeve2": false, "robot1Auto": "SUBSTATION_TERMINAL", "robot2Auto": "SUBSTATION_TERMINAL", "autoTerminal": 1, "autoJunctions": [[[], [], [], [], []], [[], [], [], [], []], [[], [], [], [], []], [[], [], [], [], []], [[], [], [], [], []]], "dcJunctions": [[[], [], [], [], []], [[], [], [], [], []], [[], [], [], [], []], [[], [], [], [], []], [[], [], [], [], []]], "dcTerminalNear": 7, "dcTerminalFar": 1, "egNavigated1": true, "egNavigated2": true, "minorPenalties": 1, "majorPenalties": 0, "autoNavigationPoints": 4, "signalBonusPoints": 0, "autoJunctionConePoints": 0, "autoTerminalConePoints": 1, "dcJunctionConePoints": 0, "dcTerminalConePoints": 8, "ownershipPoints": 0, "circuitPoints": 0, "egNavigationPoints": 4, "autoPoints": 5, "dcPoints": 8, "endgamePoints": 4, "penaltyPointsCommitted": 10, "prePenaltyTotal": 17, "autoJunctionCones": [0, 0, 0, 0], "dcJunctionCones": [0, 0, 0, 0], "beacons": 0, "ownedJunctions": 0, "circuit": false, "totalPoints": 37}]}]}