{"matches": [{"actualStartTime": "2023-02-18T11:11:58.089", "description": "Qualification 1", "tournamentLevel": "QUALIFICATION", "series": 0, "matchNumber": 1, "scoreRedFinal": 157, "scoreRedFoul": 0, "scoreRedAuto": 23, "scoreBlueFinal": 136, "scoreBlueFoul": 0, "scoreBlueAuto": 45, "postResultTime": "2023-02-18T11:19:31.25", "teams": [{"teamNumber": 13835, "station": "Red1", "dq": false, "onField": true}, {"teamNumber": 5196, "station": "Red2", "dq": false, "onField": true}, {"teamNumber": 7172, "station": "Blue1", "dq": false, "onField": true}, {"teamNumber": 20771, "station": "Blue2", "dq": false, "onField": true}], "modifiedOn": "2023-02-19T01:21:33.269"}, {"actualStartTime": "2023-02-18T11:16:37.207", "description": "Qualification 2", "tournamentLevel": "QUALIFICATION", "series": 0, "matchNumber": 2, "scoreRedFinal": 102, "scoreRedFoul": 20, "scoreRedAuto": 44, "scoreBlueFinal": 66, "scoreBlueFoul": 10, "scoreBlueAuto": 22, "postResultTime": "2023-02-18T11:26:36.314", "teams": [{"teamNumber": 18099, "station": "Red1", "dq": false, "onField": true}, {"teamNumber": 21430, "station": "Red2", "dq": false, "onField": true}, {"teamNumber": 11308, "station": "Blue1", "dq": false, "onField": true}, {"teamNumber": 13879, "station": "Blue2", "dq": false, "onField": true}], "modifiedOn": "2023-02-19T01:21:33.101"}, {"actualStartTime": "2023-02-18T11:23:09.493", "description": "Qualification 3", "tournamentLevel": "QUALIFICATION", "series": 0, "matchNumber": 3, "scoreRedFinal": 104, "scoreRedFoul": 40, "scoreRedAuto": 30, "scoreBlueFinal": 185, "scoreBlueFoul": 10, "scoreBlueAuto": 45, "postResultTime": "2023-02-18T11:31:02.661", "teams": [{"teamNumber": 19564, "station": "Red1", "dq": false, "onField": true}, {"teamNumber": 15403, "station": "Red2", "dq": false, "onField": true}, {"teamNumber": 21229, "station": "Blue1", "dq": false, "onField": true}, {"teamNumber": 15755, "station": "Blue2", "dq": false, "onField": true}], "modifiedOn": "2023-02-19T01:21:33.639"}, {"actualStartTime": "2023-02-18T11:28:05.764", "description": "Qualification 4", "tournamentLevel": "QUALIFICATION", "series": 0, "matchNumber": 4, "scoreRedFinal": 67, "scoreRedFoul": 0, "scoreRedAuto": 20, "scoreBlueFinal": 227, "scoreBlueFoul": 10, "scoreBlueAuto": 54, "postResultTime": "2023-02-18T11:37:40.361", "teams": [{"teamNumber": 10448, "station": "Red1", "dq": false, "onField": true}, {"teamNumber": 14659, "station": "Red2", "dq": false, "onField": true}, {"teamNumber": 11260, "station": "Blue1", "dq": false, "onField": true}, {"teamNumber": 19746, "station": "Blue2", "dq": false, "onField": true}], "modifiedOn": "2023-02-19T01:21:33.613"}, {"actualStartTime": "2023-02-18T11:34:40.046", "description": "Qualification 5", "tournamentLevel": "QUALIFICATION", "series": 0, "matchNumber": 5, "scoreRedFinal": 119, "scoreRedFoul": 10, "scoreRedAuto": 29, "scoreBlueFinal": 137, "scoreBlueFoul": 0, "scoreBlueAuto": 44, "postResultTime": "2023-02-18T11:41:45.645", "teams": [{"teamNumber": 17969, "station": "Red1", "dq": false, "onField": true}, {"teamNumber": 17190, "station": "Red2", "dq": false, "onField": true}, {"teamNumber": 19541, "station": "Blue1", "dq": false, "onField": true}, {"teamNumber": 19970, "station": "Blue2", "dq": false, "onField": true}], "modifiedOn": "2023-02-19T01:21:33.564"}, {"actualStartTime": "2023-02-18T11:38:49.648", "description": "Qualification 6", "tournamentLevel": "QUALIFICATION", "series": 0, "matchNumber": 6, "scoreRedFinal": 141, "scoreRedFoul": 50, "scoreRedAuto": 26, "scoreBlueFinal": 201, "scoreBlueFoul": 10, "scoreBlueAuto": 50, "postResultTime": "2023-02-18T11:47:31.431", "teams": [{"teamNumber": 21171, "station": "Red1", "dq": false, "onField": true}, {"teamNumber": 13022, "station": "Red2", "dq": false, "onField": true}, {"teamNumber": 17153, "station": "Blue1", "dq": false, "onField": true}, {"teamNumber": 8641, "station": "Blue2", "dq": false, "onField": true}], "modifiedOn": "2023-02-19T01:21:33.503"}, {"actualStartTime": "2023-02-18T11:44:29.419", "description": "Qualification 7", "tournamentLevel": "QUALIFICATION", "series": 0, "matchNumber": 7, "scoreRedFinal": 88, "scoreRedFoul": 0, "scoreRedAuto": 10, "scoreBlueFinal": 181, "scoreBlueFoul": 0, "scoreBlueAuto": 36, "postResultTime": "2023-02-18T11:53:24.735", "teams": [{"teamNumber": 16629, "station": "Red1", "dq": false, "onField": true}, {"teamNumber": 5899, "station": "Red2", "dq": false, "onField": true}, {"teamNumber": 20077, "station": "Blue1", "dq": false, "onField": true}, {"teamNumber": 22250, "station": "Blue2", "dq": false, "onField": true}], "modifiedOn": "2023-02-19T01:21:33.453"}, {"actualStartTime": "2023-02-18T11:50:28.955", "description": "Qualification 8", "tournamentLevel": "QUALIFICATION", "series": 0, "matchNumber": 8, "scoreRedFinal": 45, "scoreRedFoul": 0, "scoreRedAuto": 11, "scoreBlueFinal": 113, "scoreBlueFoul": 0, "scoreBlueAuto": 20, "postResultTime": "2023-02-18T11:58:52.477", "teams": [{"teamNumber": 21819, "station": "Red1", "dq": false, "onField": true}, {"teamNumber": 17302, "station": "Red2", "dq": false, "onField": true}, {"teamNumber": 6382, "station": "Blue1", "dq": false, "onField": true}, {"teamNumber": 17483, "station": "Blue2", "dq": false, "onField": true}], "modifiedOn": "2023-02-19T01:21:33.417"}, {"actualStartTime": "2023-02-18T11:55:42.563", "description": "Qualification 9", "tournamentLevel": "QUALIFICATION", "series": 0, "matchNumber": 9, "scoreRedFinal": 125, "scoreRedFoul": 20, "scoreRedAuto": 20, "scoreBlueFinal": 22, "scoreBlueFoul": 0, "scoreBlueAuto": 2, "postResultTime": "2023-02-18T12:03:38.856", "teams": [{"teamNumber": 14659, "station": "Red1", "dq": false, "onField": true}, {"teamNumber": 13835, "station": "Red2", "dq": false, "onField": true}, {"teamNumber": 13879, "station": "Blue1", "dq": false, "onField": true}, {"teamNumber": 19564, "station": "Blue2", "dq": false, "onField": true}], "modifiedOn": "2023-02-19T01:21:33.393"}, {"actualStartTime": "2023-02-18T12:00:26.38", "description": "Qualification 10", "tournamentLevel": "QUALIFICATION", "series": 0, "matchNumber": 10, "scoreRedFinal": 225, "scoreRedFoul": 0, "scoreRedAuto": 65, "scoreBlueFinal": 53, "scoreBlueFoul": 0, "scoreBlueAuto": 0, "postResultTime": "2023-02-18T12:13:52.509", "teams": [{"teamNumber": 19541, "station": "Red1", "dq": false, "onField": true}, {"teamNumber": 11260, "station": "Red2", "dq": false, "onField": true}, {"teamNumber": 5196, "station": "Blue1", "dq": false, "onField": true}, {"teamNumber": 18099, "station": "Blue2", "dq": false, "onField": true}], "modifiedOn": "2023-02-19T01:21:33.369"}, {"actualStartTime": "2023-02-18T12:10:34.236", "description": "Qualification 11", "tournamentLevel": "QUALIFICATION", "series": 0, "matchNumber": 11, "scoreRedFinal": 146, "scoreRedFoul": 10, "scoreRedAuto": 48, "scoreBlueFinal": 242, "scoreBlueFoul": 0, "scoreBlueAuto": 89, "postResultTime": "2023-02-18T12:18:00.276", "teams": [{"teamNumber": 13022, "station": "Red1", "dq": false, "onField": true}, {"teamNumber": 20771, "station": "Red2", "dq": false, "onField": true}, {"teamNumber": 21229, "station": "Blue1", "dq": false, "onField": true}, {"teamNumber": 17969, "station": "Blue2", "dq": false, "onField": true}], "modifiedOn": "2023-02-19T01:21:33.342"}, {"actualStartTime": "2023-02-18T12:14:51.617", "description": "Qualification 12", "tournamentLevel": "QUALIFICATION", "series": 0, "matchNumber": 12, "scoreRedFinal": 118, "scoreRedFoul": 0, "scoreRedAuto": 44, "scoreBlueFinal": 101, "scoreBlueFoul": 0, "scoreBlueAuto": 20, "postResultTime": "2023-02-18T12:24:28.614", "teams": [{"teamNumber": 15403, "station": "Red1", "dq": false, "onField": true}, {"teamNumber": 19970, "station": "Red2", "dq": false, "onField": true}, {"teamNumber": 16629, "station": "Blue1", "dq": false, "onField": true}, {"teamNumber": 11308, "station": "Blue2", "dq": false, "onField": true}], "modifiedOn": "2023-02-19T01:21:33.318"}, {"actualStartTime": "2023-02-18T12:21:10.854", "description": "Qualification 13", "tournamentLevel": "QUALIFICATION", "series": 0, "matchNumber": 13, "scoreRedFinal": 98, "scoreRedFoul": 0, "scoreRedAuto": 20, "scoreBlueFinal": 68, "scoreBlueFoul": 10, "scoreBlueAuto": 0, "postResultTime": "2023-02-18T12:30:07.938", "teams": [{"teamNumber": 20077, "station": "Red1", "dq": false, "onField": true}, {"teamNumber": 15755, "station": "Red2", "dq": false, "onField": true}, {"teamNumber": 17153, "station": "Blue1", "dq": false, "onField": true}, {"teamNumber": 17302, "station": "Blue2", "dq": false, "onField": true}], "modifiedOn": "2023-02-19T01:21:33.306"}, {"actualStartTime": "2023-02-18T12:27:05.424", "description": "Qualification 14", "tournamentLevel": "QUALIFICATION", "series": 0, "matchNumber": 14, "scoreRedFinal": 88, "scoreRedFoul": 0, "scoreRedAuto": 6, "scoreBlueFinal": 207, "scoreBlueFoul": 0, "scoreBlueAuto": 30, "postResultTime": "2023-02-18T13:06:11.572", "teams": [{"teamNumber": 21430, "station": "Red1", "dq": false, "onField": true}, {"teamNumber": 17190, "station": "Red2", "dq": false, "onField": true}, {"teamNumber": 19746, "station": "Blue1", "dq": false, "onField": true}, {"teamNumber": 21819, "station": "Blue2", "dq": false, "onField": true}], "modifiedOn": "2023-02-19T01:21:33.293"}, {"actualStartTime": "2023-02-18T13:03:06.607", "description": "Qualification 15", "tournamentLevel": "QUALIFICATION", "series": 0, "matchNumber": 15, "scoreRedFinal": 172, "scoreRedFoul": 0, "scoreRedAuto": 65, "scoreBlueFinal": 76, "scoreBlueFoul": 10, "scoreBlueAuto": 15, "postResultTime": "2023-02-18T13:11:46.683", "teams": [{"teamNumber": 17483, "station": "Red1", "dq": false, "onField": true}, {"teamNumber": 21171, "station": "Red2", "dq": false, "onField": true}, {"teamNumber": 5899, "station": "Blue1", "dq": false, "onField": true}, {"teamNumber": 10448, "station": "Blue2", "dq": false, "onField": true}], "modifiedOn": "2023-02-19T01:21:33.281"}, {"actualStartTime": "2023-02-18T13:08:13.8", "description": "Qualification 16", "tournamentLevel": "QUALIFICATION", "series": 0, "matchNumber": 16, "scoreRedFinal": 158, "scoreRedFoul": 0, "scoreRedAuto": 30, "scoreBlueFinal": 88, "scoreBlueFoul": 0, "scoreBlueAuto": 20, "postResultTime": "2023-02-18T13:16:01.419", "teams": [{"teamNumber": 8641, "station": "Red1", "dq": false, "onField": true}, {"teamNumber": 7172, "station": "Red2", "dq": false, "onField": true}, {"teamNumber": 22250, "station": "Blue1", "dq": false, "onField": true}, {"teamNumber": 6382, "station": "Blue2", "dq": false, "onField": true}], "modifiedOn": "2023-02-19T01:21:33.256"}, {"actualStartTime": "2023-02-18T13:12:57.568", "description": "Qualification 17", "tournamentLevel": "QUALIFICATION", "series": 0, "matchNumber": 17, "scoreRedFinal": 147, "scoreRedFoul": 20, "scoreRedAuto": 46, "scoreBlueFinal": 107, "scoreBlueFoul": 50, "scoreBlueAuto": 0, "postResultTime": "2023-02-18T13:23:22.189", "teams": [{"teamNumber": 18099, "station": "Red1", "dq": false, "onField": true}, {"teamNumber": 13835, "station": "Red2", "dq": false, "onField": true}, {"teamNumber": 19970, "station": "Blue1", "dq": false, "onField": true}, {"teamNumber": 13022, "station": "Blue2", "dq": false, "onField": true}], "modifiedOn": "2023-02-19T01:21:33.601"}, {"actualStartTime": "2023-02-18T13:20:21.254", "description": "Qualification 18", "tournamentLevel": "QUALIFICATION", "series": 0, "matchNumber": 18, "scoreRedFinal": 225, "scoreRedFoul": 0, "scoreRedAuto": 70, "scoreBlueFinal": 33, "scoreBlueFoul": 0, "scoreBlueAuto": 0, "postResultTime": "2023-02-18T13:28:01.754", "teams": [{"teamNumber": 19541, "station": "Red1", "dq": false, "onField": true}, {"teamNumber": 21229, "station": "Red2", "dq": false, "onField": true}, {"teamNumber": 17302, "station": "Blue1", "dq": false, "onField": true}, {"teamNumber": 16629, "station": "Blue2", "dq": false, "onField": true}], "modifiedOn": "2023-02-19T01:21:33.232"}, {"actualStartTime": "2023-02-18T13:24:44.256", "description": "Qualification 19", "tournamentLevel": "QUALIFICATION", "series": 0, "matchNumber": 19, "scoreRedFinal": 242, "scoreRedFoul": 0, "scoreRedAuto": 64, "scoreBlueFinal": 180, "scoreBlueFoul": 30, "scoreBlueAuto": 44, "postResultTime": "2023-02-18T13:32:36.675", "teams": [{"teamNumber": 15403, "station": "Red1", "dq": false, "onField": true}, {"teamNumber": 11260, "station": "Red2", "dq": false, "onField": true}, {"teamNumber": 21430, "station": "Blue1", "dq": false, "onField": true}, {"teamNumber": 20077, "station": "Blue2", "dq": false, "onField": true}], "modifiedOn": "2023-02-19T01:21:33.577"}, {"actualStartTime": "2023-02-18T13:29:30.912", "description": "Qualification 20", "tournamentLevel": "QUALIFICATION", "series": 0, "matchNumber": 20, "scoreRedFinal": 150, "scoreRedFoul": 40, "scoreRedAuto": 27, "scoreBlueFinal": 143, "scoreBlueFoul": 0, "scoreBlueAuto": 30, "postResultTime": "2023-02-18T13:38:04.93", "teams": [{"teamNumber": 13879, "station": "Red1", "dq": false, "onField": true}, {"teamNumber": 19746, "station": "Red2", "dq": false, "onField": true}, {"teamNumber": 5899, "station": "Blue1", "dq": false, "onField": true}, {"teamNumber": 5196, "station": "Blue2", "dq": false, "onField": true}], "modifiedOn": "2023-02-19T01:21:33.207"}, {"actualStartTime": "2023-02-18T13:34:55.894", "description": "Qualification 21", "tournamentLevel": "QUALIFICATION", "series": 0, "matchNumber": 21, "scoreRedFinal": 74, "scoreRedFoul": 0, "scoreRedAuto": 2, "scoreBlueFinal": 153, "scoreBlueFoul": 10, "scoreBlueAuto": 44, "postResultTime": "2023-02-18T13:42:27.52", "teams": [{"teamNumber": 17153, "station": "Red1", "dq": false, "onField": true}, {"teamNumber": 21819, "station": "Red2", "dq": false, "onField": true}, {"teamNumber": 11308, "station": "Blue1", "dq": false, "onField": true}, {"teamNumber": 14659, "station": "Blue2", "dq": false, "onField": true}], "modifiedOn": "2023-02-19T01:21:33.54"}, {"actualStartTime": "2023-02-18T13:39:27.509", "description": "Qualification 22", "tournamentLevel": "QUALIFICATION", "series": 0, "matchNumber": 22, "scoreRedFinal": 81, "scoreRedFoul": 0, "scoreRedAuto": 22, "scoreBlueFinal": 86, "scoreBlueFoul": 0, "scoreBlueAuto": 5, "postResultTime": "2023-02-18T13:47:16.362", "teams": [{"teamNumber": 17483, "station": "Red1", "dq": false, "onField": true}, {"teamNumber": 20771, "station": "Red2", "dq": false, "onField": true}, {"teamNumber": 8641, "station": "Blue1", "dq": false, "onField": true}, {"teamNumber": 19564, "station": "Blue2", "dq": false, "onField": true}], "modifiedOn": "2023-02-19T01:21:33.18"}, {"actualStartTime": "2023-02-18T13:44:11.919", "description": "Qualification 23", "tournamentLevel": "QUALIFICATION", "series": 0, "matchNumber": 23, "scoreRedFinal": 186, "scoreRedFoul": 10, "scoreRedAuto": 50, "scoreBlueFinal": 26, "scoreBlueFoul": 0, "scoreBlueAuto": 2, "postResultTime": "2023-02-18T13:51:45.379", "teams": [{"teamNumber": 7172, "station": "Red1", "dq": false, "onField": true}, {"teamNumber": 10448, "station": "Red2", "dq": false, "onField": true}, {"teamNumber": 15755, "station": "Blue1", "dq": false, "onField": true}, {"teamNumber": 17190, "station": "Blue2", "dq": false, "onField": true}], "modifiedOn": "2023-02-19T01:21:33.515"}, {"actualStartTime": "2023-02-18T13:48:39.853", "description": "Qualification 24", "tournamentLevel": "QUALIFICATION", "series": 0, "matchNumber": 24, "scoreRedFinal": 107, "scoreRedFoul": 0, "scoreRedAuto": 23, "scoreBlueFinal": 210, "scoreBlueFoul": 0, "scoreBlueAuto": 59, "postResultTime": "2023-02-18T13:56:21.674", "teams": [{"teamNumber": 22250, "station": "Red1", "dq": false, "onField": true}, {"teamNumber": 21171, "station": "Red2", "dq": false, "onField": true}, {"teamNumber": 6382, "station": "Blue1", "dq": false, "onField": true}, {"teamNumber": 17969, "station": "Blue2", "dq": false, "onField": true}], "modifiedOn": "2023-02-19T01:21:33.154"}, {"actualStartTime": "2023-02-18T13:53:14.471", "description": "Qualification 25", "tournamentLevel": "QUALIFICATION", "series": 0, "matchNumber": 25, "scoreRedFinal": 65, "scoreRedFoul": 0, "scoreRedAuto": 22, "scoreBlueFinal": 159, "scoreBlueFoul": 0, "scoreBlueAuto": 50, "postResultTime": "2023-02-18T14:00:32.994", "teams": [{"teamNumber": 13022, "station": "Red1", "dq": false, "onField": true}, {"teamNumber": 13879, "station": "Red2", "dq": false, "onField": true}, {"teamNumber": 16629, "station": "Blue1", "dq": false, "onField": true}, {"teamNumber": 11260, "station": "Blue2", "dq": false, "onField": true}], "modifiedOn": "2023-02-19T01:21:33.478"}, {"actualStartTime": "2023-02-18T13:57:33.831", "description": "Qualification 26", "tournamentLevel": "QUALIFICATION", "series": 0, "matchNumber": 26, "scoreRedFinal": 125, "scoreRedFoul": 0, "scoreRedAuto": 15, "scoreBlueFinal": 132, "scoreBlueFoul": 0, "scoreBlueAuto": 46, "postResultTime": "2023-02-18T14:04:59.145", "teams": [{"teamNumber": 17302, "station": "Red1", "dq": false, "onField": true}, {"teamNumber": 5899, "station": "Red2", "dq": false, "onField": true}, {"teamNumber": 13835, "station": "Blue1", "dq": false, "onField": true}, {"teamNumber": 21430, "station": "Blue2", "dq": false, "onField": true}], "modifiedOn": "2023-02-19T01:21:33.141"}, {"actualStartTime": "2023-02-18T14:01:47.637", "description": "Qualification 27", "tournamentLevel": "QUALIFICATION", "series": 0, "matchNumber": 27, "scoreRedFinal": 295, "scoreRedFoul": 0, "scoreRedAuto": 80, "scoreBlueFinal": 57, "scoreBlueFoul": 60, "scoreBlueAuto": 4, "postResultTime": "2023-02-18T14:09:27.8", "teams": [{"teamNumber": 8641, "station": "Red1", "dq": false, "onField": true}, {"teamNumber": 21229, "station": "Red2", "dq": false, "onField": true}, {"teamNumber": 19970, "station": "Blue1", "dq": false, "onField": true}, {"teamNumber": 14659, "station": "Blue2", "dq": false, "onField": true}], "modifiedOn": "2023-02-19T01:21:33.466"}, {"actualStartTime": "2023-02-18T14:06:28.309", "description": "Qualification 28", "tournamentLevel": "QUALIFICATION", "series": 0, "matchNumber": 28, "scoreRedFinal": 258, "scoreRedFoul": 10, "scoreRedAuto": 56, "scoreBlueFinal": 88, "scoreBlueFoul": 30, "scoreBlueAuto": 3, "postResultTime": "2023-02-18T14:14:02.874", "teams": [{"teamNumber": 5196, "station": "Red1", "dq": false, "onField": true}, {"teamNumber": 20077, "station": "Red2", "dq": false, "onField": true}, {"teamNumber": 17190, "station": "Blue1", "dq": false, "onField": true}, {"teamNumber": 11308, "station": "Blue2", "dq": false, "onField": true}], "modifiedOn": "2023-02-19T01:21:33.129"}, {"actualStartTime": "2023-02-18T14:10:56.294", "description": "Qualification 29", "tournamentLevel": "QUALIFICATION", "series": 0, "matchNumber": 29, "scoreRedFinal": 220, "scoreRedFoul": 0, "scoreRedAuto": 59, "scoreBlueFinal": 150, "scoreBlueFoul": 0, "scoreBlueAuto": 20, "postResultTime": "2023-02-18T14:18:49.575", "teams": [{"teamNumber": 17969, "station": "Red1", "dq": false, "onField": true}, {"teamNumber": 19746, "station": "Red2", "dq": false, "onField": true}, {"teamNumber": 15403, "station": "Blue1", "dq": false, "onField": true}, {"teamNumber": 17483, "station": "Blue2", "dq": false, "onField": true}], "modifiedOn": "2023-02-19T01:21:33.441"}, {"actualStartTime": "2023-02-18T14:15:48.709", "description": "Qualification 30", "tournamentLevel": "QUALIFICATION", "series": 0, "matchNumber": 30, "scoreRedFinal": 112, "scoreRedFoul": 0, "scoreRedAuto": 30, "scoreBlueFinal": 158, "scoreBlueFoul": 0, "scoreBlueAuto": 58, "postResultTime": "2023-02-18T14:23:51.594", "teams": [{"teamNumber": 19564, "station": "Red1", "dq": false, "onField": true}, {"teamNumber": 7172, "station": "Red2", "dq": false, "onField": true}, {"teamNumber": 21171, "station": "Blue1", "dq": false, "onField": true}, {"teamNumber": 19541, "station": "Blue2", "dq": false, "onField": true}], "modifiedOn": "2023-02-19T01:21:33.115"}, {"actualStartTime": "2023-02-18T14:20:09.876", "description": "Qualification 31", "tournamentLevel": "QUALIFICATION", "series": 0, "matchNumber": 31, "scoreRedFinal": 145, "scoreRedFoul": 10, "scoreRedAuto": 24, "scoreBlueFinal": 65, "scoreBlueFoul": 0, "scoreBlueAuto": 2, "postResultTime": "2023-02-18T14:27:59.858", "teams": [{"teamNumber": 20771, "station": "Red1", "dq": false, "onField": true}, {"teamNumber": 22250, "station": "Red2", "dq": false, "onField": true}, {"teamNumber": 21819, "station": "Blue1", "dq": false, "onField": true}, {"teamNumber": 15755, "station": "Blue2", "dq": false, "onField": true}], "modifiedOn": "2023-02-19T01:21:33.429"}, {"actualStartTime": "2023-02-18T14:25:00.005", "description": "Qualification 32", "tournamentLevel": "QUALIFICATION", "series": 0, "matchNumber": 32, "scoreRedFinal": 110, "scoreRedFoul": 50, "scoreRedAuto": 0, "scoreBlueFinal": 116, "scoreBlueFoul": 10, "scoreBlueAuto": 20, "postResultTime": "2023-02-18T14:34:10.416", "teams": [{"teamNumber": 10448, "station": "Red1", "dq": false, "onField": true}, {"teamNumber": 6382, "station": "Red2", "dq": false, "onField": true}, {"teamNumber": 18099, "station": "Blue1", "dq": false, "onField": true}, {"teamNumber": 17153, "station": "Blue2", "dq": false, "onField": true}], "modifiedOn": "2023-02-19T01:21:33.086"}, {"actualStartTime": "2023-02-18T14:31:06.907", "description": "Qualification 33", "tournamentLevel": "QUALIFICATION", "series": 0, "matchNumber": 33, "scoreRedFinal": 138, "scoreRedFoul": 10, "scoreRedAuto": 45, "scoreBlueFinal": 222, "scoreBlueFoul": 0, "scoreBlueAuto": 60, "postResultTime": "2023-02-18T14:38:39.031", "teams": [{"teamNumber": 11308, "station": "Red1", "dq": false, "onField": true}, {"teamNumber": 8641, "station": "Red2", "dq": false, "onField": true}, {"teamNumber": 11260, "station": "Blue1", "dq": false, "onField": true}, {"teamNumber": 13835, "station": "Blue2", "dq": false, "onField": true}], "modifiedOn": "2023-02-19T01:21:33.244"}, {"actualStartTime": "2023-02-18T14:35:30.069", "description": "Qualification 34", "tournamentLevel": "QUALIFICATION", "series": 0, "matchNumber": 34, "scoreRedFinal": 28, "scoreRedFoul": 0, "scoreRedAuto": 0, "scoreBlueFinal": 107, "scoreBlueFoul": 0, "scoreBlueAuto": 25, "postResultTime": "2023-02-18T14:43:26.198", "teams": [{"teamNumber": 17190, "station": "Red1", "dq": false, "onField": true}, {"teamNumber": 13879, "station": "Red2", "dq": false, "onField": true}, {"teamNumber": 17302, "station": "Blue1", "dq": false, "onField": true}, {"teamNumber": 15403, "station": "Blue2", "dq": false, "onField": true}], "modifiedOn": "2023-02-19T01:21:33.405"}, {"actualStartTime": "2023-02-18T14:40:11.61", "description": "Qualification 35", "tournamentLevel": "QUALIFICATION", "series": 0, "matchNumber": 35, "scoreRedFinal": 218, "scoreRedFoul": 0, "scoreRedAuto": 70, "scoreBlueFinal": 191, "scoreBlueFoul": 0, "scoreBlueAuto": 50, "postResultTime": "2023-02-18T14:48:12.792", "teams": [{"teamNumber": 21229, "station": "Red1", "dq": false, "onField": true}, {"teamNumber": 20077, "station": "Red2", "dq": false, "onField": true}, {"teamNumber": 17483, "station": "Blue1", "dq": false, "onField": true}, {"teamNumber": 7172, "station": "Blue2", "dq": false, "onField": true}], "modifiedOn": "2023-02-19T01:21:33.589"}, {"actualStartTime": "2023-02-18T14:45:10.365", "description": "Qualification 36", "tournamentLevel": "QUALIFICATION", "series": 0, "matchNumber": 36, "scoreRedFinal": 117, "scoreRedFoul": 0, "scoreRedAuto": 24, "scoreBlueFinal": 150, "scoreBlueFoul": 10, "scoreBlueAuto": 40, "postResultTime": "2023-02-18T14:52:56.286", "teams": [{"teamNumber": 14659, "station": "Red1", "dq": false, "onField": true}, {"teamNumber": 16629, "station": "Red2", "dq": false, "onField": true}, {"teamNumber": 20771, "station": "Blue1", "dq": false, "onField": true}, {"teamNumber": 21171, "station": "Blue2", "dq": false, "onField": true}], "modifiedOn": "2023-02-19T01:21:33.675"}, {"actualStartTime": "2023-02-18T14:49:51.929", "description": "Qualification 37", "tournamentLevel": "QUALIFICATION", "series": 0, "matchNumber": 37, "scoreRedFinal": 131, "scoreRedFoul": 0, "scoreRedAuto": 20, "scoreBlueFinal": 55, "scoreBlueFoul": 10, "scoreBlueAuto": 2, "postResultTime": "2023-02-18T14:57:22.612", "teams": [{"teamNumber": 19970, "station": "Red1", "dq": false, "onField": true}, {"teamNumber": 5196, "station": "Red2", "dq": false, "onField": true}, {"teamNumber": 21819, "station": "Blue1", "dq": false, "onField": true}, {"teamNumber": 10448, "station": "Blue2", "dq": false, "onField": true}], "modifiedOn": "2023-02-19T01:21:33.219"}, {"actualStartTime": "2023-02-18T14:54:21.443", "description": "Qualification 38", "tournamentLevel": "QUALIFICATION", "series": 0, "matchNumber": 38, "scoreRedFinal": 52, "scoreRedFoul": 0, "scoreRedAuto": 20, "scoreBlueFinal": 147, "scoreBlueFoul": 0, "scoreBlueAuto": 24, "postResultTime": "2023-02-18T15:02:31.662", "teams": [{"teamNumber": 19564, "station": "Red1", "dq": false, "onField": true}, {"teamNumber": 6382, "station": "Red2", "dq": false, "onField": true}, {"teamNumber": 21430, "station": "Blue1", "dq": false, "onField": true}, {"teamNumber": 13022, "station": "Blue2", "dq": false, "onField": true}], "modifiedOn": "2023-02-19T01:21:33.381"}, {"actualStartTime": "2023-02-18T14:59:21.661", "description": "Qualification 39", "tournamentLevel": "QUALIFICATION", "series": 0, "matchNumber": 39, "scoreRedFinal": 87, "scoreRedFoul": 20, "scoreRedAuto": 0, "scoreBlueFinal": 233, "scoreBlueFoul": 10, "scoreBlueAuto": 65, "postResultTime": "2023-02-18T15:06:40.677", "teams": [{"teamNumber": 22250, "station": "Red1", "dq": false, "onField": true}, {"teamNumber": 17153, "station": "Red2", "dq": false, "onField": true}, {"teamNumber": 19746, "station": "Blue1", "dq": false, "onField": true}, {"teamNumber": 19541, "station": "Blue2", "dq": false, "onField": true}], "modifiedOn": "2023-02-19T01:21:33.551"}, {"actualStartTime": "2023-02-18T15:03:44.545", "description": "Qualification 40", "tournamentLevel": "QUALIFICATION", "series": 0, "matchNumber": 40, "scoreRedFinal": 181, "scoreRedFoul": 0, "scoreRedAuto": 39, "scoreBlueFinal": 37, "scoreBlueFoul": 0, "scoreBlueAuto": 0, "postResultTime": "2023-02-18T15:11:17.523", "teams": [{"teamNumber": 5899, "station": "Red1", "dq": false, "onField": true}, {"teamNumber": 17969, "station": "Red2", "dq": false, "onField": true}, {"teamNumber": 15755, "station": "Blue1", "dq": false, "onField": true}, {"teamNumber": 18099, "station": "Blue2", "dq": false, "onField": true}], "modifiedOn": "2023-02-19T01:21:33.663"}, {"actualStartTime": "2023-02-18T15:08:11.521", "description": "Qualification 41", "tournamentLevel": "QUALIFICATION", "series": 0, "matchNumber": 41, "scoreRedFinal": 36, "scoreRedFoul": 0, "scoreRedAuto": 12, "scoreBlueFinal": 160, "scoreBlueFoul": 0, "scoreBlueAuto": 38, "postResultTime": "2023-02-18T15:15:50.637", "teams": [{"teamNumber": 17190, "station": "Red1", "dq": false, "onField": true}, {"teamNumber": 16629, "station": "Red2", "dq": false, "onField": true}, {"teamNumber": 13835, "station": "Blue1", "dq": false, "onField": true}, {"teamNumber": 17483, "station": "Blue2", "dq": false, "onField": true}], "modifiedOn": "2023-02-19T01:21:33.193"}, {"actualStartTime": "2023-02-18T15:12:47.353", "description": "Qualification 42", "tournamentLevel": "QUALIFICATION", "series": 0, "matchNumber": 42, "scoreRedFinal": 175, "scoreRedFoul": 20, "scoreRedAuto": 55, "scoreBlueFinal": 156, "scoreBlueFoul": 0, "scoreBlueAuto": 35, "postResultTime": "2023-02-18T15:20:39.196", "teams": [{"teamNumber": 11260, "station": "Red1", "dq": false, "onField": true}, {"teamNumber": 19970, "station": "Red2", "dq": false, "onField": true}, {"teamNumber": 21171, "station": "Blue1", "dq": false, "onField": true}, {"teamNumber": 17302, "station": "Blue2", "dq": false, "onField": true}], "modifiedOn": "2023-02-19T01:21:33.357"}, {"actualStartTime": "2023-02-18T15:17:11.051", "description": "Qualification 43", "tournamentLevel": "QUALIFICATION", "series": 0, "matchNumber": 43, "scoreRedFinal": 182, "scoreRedFoul": 10, "scoreRedAuto": 45, "scoreBlueFinal": 118, "scoreBlueFoul": 0, "scoreBlueAuto": 20, "postResultTime": "2023-02-18T15:24:58.975", "teams": [{"teamNumber": 7172, "station": "Red1", "dq": false, "onField": true}, {"teamNumber": 21819, "station": "Red2", "dq": false, "onField": true}, {"teamNumber": 13022, "station": "Blue1", "dq": false, "onField": true}, {"teamNumber": 15403, "station": "Blue2", "dq": false, "onField": true}], "modifiedOn": "2023-02-19T01:21:33.527"}, {"actualStartTime": "2023-02-18T15:21:54.546", "description": "Qualification 44", "tournamentLevel": "QUALIFICATION", "series": 0, "matchNumber": 44, "scoreRedFinal": 125, "scoreRedFoul": 0, "scoreRedAuto": 40, "scoreBlueFinal": 180, "scoreBlueFoul": 0, "scoreBlueAuto": 52, "postResultTime": "2023-02-18T15:29:28.34", "teams": [{"teamNumber": 10448, "station": "Red1", "dq": false, "onField": true}, {"teamNumber": 22250, "station": "Red2", "dq": false, "onField": true}, {"teamNumber": 13879, "station": "Blue1", "dq": false, "onField": true}, {"teamNumber": 21229, "station": "Blue2", "dq": false, "onField": true}], "modifiedOn": "2023-02-19T01:21:33.651"}, {"actualStartTime": "2023-02-18T15:26:19.938", "description": "Qualification 45", "tournamentLevel": "QUALIFICATION", "series": 0, "matchNumber": 45, "scoreRedFinal": 155, "scoreRedFoul": 10, "scoreRedAuto": 20, "scoreBlueFinal": 134, "scoreBlueFoul": 10, "scoreBlueAuto": 30, "postResultTime": "2023-02-18T15:33:41.211", "teams": [{"teamNumber": 6382, "station": "Red1", "dq": false, "onField": true}, {"teamNumber": 11308, "station": "Red2", "dq": false, "onField": true}, {"teamNumber": 20771, "station": "Blue1", "dq": false, "onField": true}, {"teamNumber": 5899, "station": "Blue2", "dq": false, "onField": true}], "modifiedOn": "2023-02-19T01:21:33.167"}, {"actualStartTime": "2023-02-18T15:30:38.073", "description": "Qualification 46", "tournamentLevel": "QUALIFICATION", "series": 0, "matchNumber": 46, "scoreRedFinal": 133, "scoreRedFoul": 10, "scoreRedAuto": 20, "scoreBlueFinal": 188, "scoreBlueFoul": 0, "scoreBlueAuto": 39, "postResultTime": "2023-02-18T15:41:19.665", "teams": [{"teamNumber": 5196, "station": "Red1", "dq": false, "onField": true}, {"teamNumber": 17153, "station": "Red2", "dq": false, "onField": true}, {"teamNumber": 17969, "station": "Blue1", "dq": false, "onField": true}, {"teamNumber": 19564, "station": "Blue2", "dq": false, "onField": true}], "modifiedOn": "2023-02-19T01:21:33.33"}, {"actualStartTime": "2023-02-18T15:38:10.68", "description": "Qualification 47", "tournamentLevel": "QUALIFICATION", "series": 0, "matchNumber": 47, "scoreRedFinal": 51, "scoreRedFoul": 10, "scoreRedAuto": 23, "scoreBlueFinal": 135, "scoreBlueFoul": 0, "scoreBlueAuto": 24, "postResultTime": "2023-02-18T15:46:17.979", "teams": [{"teamNumber": 15755, "station": "Red1", "dq": false, "onField": true}, {"teamNumber": 19541, "station": "Red2", "dq": false, "onField": true}, {"teamNumber": 14659, "station": "Blue1", "dq": false, "onField": true}, {"teamNumber": 21430, "station": "Blue2", "dq": false, "onField": true}], "modifiedOn": "2023-02-19T01:21:33.491"}, {"actualStartTime": "2023-02-18T15:43:13.351", "description": "Qualification 48", "tournamentLevel": "QUALIFICATION", "series": 0, "matchNumber": 48, "scoreRedFinal": 191, "scoreRedFoul": 0, "scoreRedAuto": 45, "scoreBlueFinal": 206, "scoreBlueFoul": 0, "scoreBlueAuto": 66, "postResultTime": "2023-02-18T15:47:42.893", "teams": [{"teamNumber": 19746, "station": "Red1", "dq": false, "onField": true}, {"teamNumber": 18099, "station": "Red2", "dq": false, "onField": true}, {"teamNumber": 20077, "station": "Blue1", "dq": false, "onField": true}, {"teamNumber": 8641, "station": "Blue2", "dq": false, "onField": true}], "modifiedOn": "2023-02-19T01:21:33.627"}, {"actualStartTime": "2023-02-18T16:37:22.942", "description": "Semifinal 1 Match 1", "tournamentLevel": "SEMIFINAL", "series": 1, "matchNumber": 1, "scoreRedFinal": 307, "scoreRedFoul": 10, "scoreRedAuto": 95, "scoreBlueFinal": 136, "scoreBlueFoul": 10, "scoreBlueAuto": 52, "postResultTime": "2023-02-18T16:41:52.56", "teams": [{"teamNumber": 21229, "station": "Red1", "dq": false, "onField": true}, {"teamNumber": 19746, "station": "Red2", "dq": false, "onField": true}, {"teamNumber": 20077, "station": "Red3", "dq": false, "onField": false}, {"teamNumber": 19541, "station": "Blue1", "dq": false, "onField": true}, {"teamNumber": 19970, "station": "Blue2", "dq": false, "onField": false}, {"teamNumber": 20771, "station": "Blue3", "dq": false, "onField": true}], "modifiedOn": "2023-02-19T01:21:33.738"}, {"actualStartTime": "2023-02-18T16:43:56.004", "description": "Semifinal 2 Match 1", "tournamentLevel": "SEMIFINAL", "series": 2, "matchNumber": 1, "scoreRedFinal": 240, "scoreRedFoul": 0, "scoreRedAuto": 84, "scoreBlueFinal": 194, "scoreBlueFoul": 0, "scoreBlueAuto": 68, "postResultTime": "2023-02-18T16:48:47.415", "teams": [{"teamNumber": 11260, "station": "Red1", "dq": false, "onField": true}, {"teamNumber": 17969, "station": "Red2", "dq": false, "onField": true}, {"teamNumber": 15403, "station": "Red3", "dq": false, "onField": false}, {"teamNumber": 13835, "station": "Blue1", "dq": false, "onField": true}, {"teamNumber": 7172, "station": "Blue2", "dq": false, "onField": true}, {"teamNumber": 6382, "station": "Blue3", "dq": false, "onField": false}], "modifiedOn": "2023-02-19T01:21:33.717"}, {"actualStartTime": "2023-02-18T16:51:30.428", "description": "Semifinal 1 Match 2", "tournamentLevel": "SEMIFINAL", "series": 1, "matchNumber": 2, "scoreRedFinal": 197, "scoreRedFoul": 60, "scoreRedAuto": 45, "scoreBlueFinal": 182, "scoreBlueFoul": 10, "scoreBlueAuto": 20, "postResultTime": "2023-02-18T16:56:42.962", "teams": [{"teamNumber": 21229, "station": "Red1", "dq": false, "onField": false}, {"teamNumber": 19746, "station": "Red2", "dq": false, "onField": true}, {"teamNumber": 20077, "station": "Red3", "dq": false, "onField": true}, {"teamNumber": 19541, "station": "Blue1", "dq": false, "onField": false}, {"teamNumber": 19970, "station": "Blue2", "dq": false, "onField": true}, {"teamNumber": 20771, "station": "Blue3", "dq": false, "onField": true}], "modifiedOn": "2023-02-19T01:21:33.702"}, {"actualStartTime": "2023-02-18T16:58:27.413", "description": "Semifinal 2 Match 2", "tournamentLevel": "SEMIFINAL", "series": 2, "matchNumber": 2, "scoreRedFinal": 264, "scoreRedFoul": 0, "scoreRedAuto": 69, "scoreBlueFinal": 224, "scoreBlueFoul": 40, "scoreBlueAuto": 70, "postResultTime": "2023-02-18T17:04:25.184", "teams": [{"teamNumber": 11260, "station": "Red1", "dq": false, "onField": true}, {"teamNumber": 17969, "station": "Red2", "dq": false, "onField": false}, {"teamNumber": 15403, "station": "Red3", "dq": false, "onField": true}, {"teamNumber": 13835, "station": "Blue1", "dq": false, "onField": false}, {"teamNumber": 7172, "station": "Blue2", "dq": false, "onField": true}, {"teamNumber": 6382, "station": "Blue3", "dq": false, "onField": true}], "modifiedOn": "2023-02-19T01:21:33.687"}, {"actualStartTime": "2023-02-18T17:16:03.186", "description": "Finals Match 1", "tournamentLevel": "FINAL", "series": 0, "matchNumber": 1, "scoreRedFinal": 248, "scoreRedFoul": 10, "scoreRedAuto": 85, "scoreBlueFinal": 181, "scoreBlueFoul": 10, "scoreBlueAuto": 65, "postResultTime": "2023-02-18T17:21:14.427", "teams": [{"teamNumber": 21229, "station": "Red1", "dq": false, "onField": true}, {"teamNumber": 19746, "station": "Red2", "dq": false, "onField": true}, {"teamNumber": 20077, "station": "Red3", "dq": false, "onField": false}, {"teamNumber": 11260, "station": "Blue1", "dq": false, "onField": true}, {"teamNumber": 17969, "station": "Blue2", "dq": false, "onField": false}, {"teamNumber": 15403, "station": "Blue3", "dq": false, "onField": true}], "modifiedOn": "2023-02-19T01:21:33.77"}, {"actualStartTime": "2023-02-18T17:30:55.291", "description": "Finals Match 2", "tournamentLevel": "FINAL", "series": 0, "matchNumber": 2, "scoreRedFinal": 219, "scoreRedFoul": 0, "scoreRedAuto": 50, "scoreBlueFinal": 204, "scoreBlueFoul": 0, "scoreBlueAuto": 81, "postResultTime": "2023-02-18T17:34:59.383", "teams": [{"teamNumber": 21229, "station": "Red1", "dq": false, "onField": true}, {"teamNumber": 19746, "station": "Red2", "dq": false, "onField": false}, {"teamNumber": 20077, "station": "Red3", "dq": false, "onField": true}, {"teamNumber": 11260, "station": "Blue1", "dq": false, "onField": true}, {"teamNumber": 17969, "station": "Blue2", "dq": false, "onField": true}, {"teamNumber": 15403, "station": "Blue3", "dq": false, "onField": false}], "modifiedOn": "2023-02-19T01:21:33.753"}]}