{"MatchScores": [{"matchLevel": "QUALIFICATION", "matchSeries": 0, "matchNumber": 1, "randomization": 5, "alliances": [{"alliance": "Blue", "team": 0, "sideOfField": "SCORING_SIDE", "initSignalSleeve1": true, "initSignalSleeve2": false, "robot1Auto": "NONE", "robot2Auto": "NONE", "autoTerminal": 0, "autoJunctions": [[[], [], [], [], []], [[], [], [], [], []], [[], [], [], [], []], [[], [], [], [], []], [[], [], [], [], []]], "dcJunctions": [[[], [], ["MY_CONE"], [], []], [[], [], [], ["OTHER_CONE"], []], [["MY_CONE"], [], ["MY_CONE"], [], []], [[], [], [], ["OTHER_CONE", "OTHER_CONE", "OTHER_CONE", "OTHER_CONE"], []], [["MY_CONE"], [], ["MY_CONE"], [], []]], "dcTerminalNear": 1, "dcTerminalFar": 0, "egNavigated1": false, "egNavigated2": true, "minorPenalties": 0, "majorPenalties": 0, "autoNavigationPoints": 0, "signalBonusPoints": 0, "autoJunctionConePoints": 0, "autoTerminalConePoints": 0, "dcJunctionConePoints": 10, "dcTerminalConePoints": 1, "ownershipPoints": 15, "circuitPoints": 0, "egNavigationPoints": 2, "autoPoints": 0, "dcPoints": 11, "endgamePoints": 17, "penaltyPointsCommitted": 0, "prePenaltyTotal": 28, "autoJunctionCones": [0, 0, 0, 0], "dcJunctionCones": [5, 0, 0, 0], "beacons": 0, "ownedJunctions": 5, "circuit": false, "totalPoints": 28}, {"alliance": "Red", "team": 0, "sideOfField": "SCORING_SIDE", "initSignalSleeve1": true, "initSignalSleeve2": false, "robot1Auto": "SUBSTATION_TERMINAL", "robot2Auto": "NONE", "autoTerminal": 0, "autoJunctions": [[[], [], [], [], []], [[], [], [], [], []], [[], [], [], [], []], [[], [], [], [], []], [[], [], [], [], []]], "dcJunctions": [[[], [], ["OTHER_CONE"], [], []], [[], [], [], ["MY_CONE"], []], [["OTHER_CONE"], [], ["OTHER_CONE"], [], []], [[], [], [], ["MY_CONE", "MY_CONE", "MY_CONE", "MY_CONE"], []], [["OTHER_CONE"], [], ["OTHER_CONE"], [], []]], "dcTerminalNear": 0, "dcTerminalFar": 0, "egNavigated1": false, "egNavigated2": false, "minorPenalties": 0, "majorPenalties": 0, "autoNavigationPoints": 2, "signalBonusPoints": 0, "autoJunctionConePoints": 0, "autoTerminalConePoints": 0, "dcJunctionConePoints": 20, "dcTerminalConePoints": 0, "ownershipPoints": 6, "circuitPoints": 0, "egNavigationPoints": 0, "autoPoints": 2, "dcPoints": 20, "endgamePoints": 6, "penaltyPointsCommitted": 0, "prePenaltyTotal": 28, "autoJunctionCones": [0, 0, 0, 0], "dcJunctionCones": [0, 0, 5, 0], "beacons": 0, "ownedJunctions": 2, "circuit": false, "totalPoints": 28}]}, {"matchLevel": "QUALIFICATION", "matchSeries": 0, "matchNumber": 2, "randomization": 1, "alliances": [{"alliance": "Blue", "team": 0, "sideOfField": "SCORING_SIDE", "initSignalSleeve1": false, "initSignalSleeve2": false, "robot1Auto": "NONE", "robot2Auto": "NONE", "autoTerminal": 0, "autoJunctions": [[[], [], [], [], []], [[], [], [], [], []], [[], [], [], [], []], [[], [], [], [], []], [[], [], [], [], []]], "dcJunctions": [[[], [], [], [], []], [[], [], [], [], []], [[], [], [], [], []], [[], [], [], [], []], [[], [], [], [], []]], "dcTerminalNear": 0, "dcTerminalFar": 0, "egNavigated1": false, "egNavigated2": false, "minorPenalties": 0, "majorPenalties": 0, "autoNavigationPoints": 0, "signalBonusPoints": 0, "autoJunctionConePoints": 0, "autoTerminalConePoints": 0, "dcJunctionConePoints": 0, "dcTerminalConePoints": 0, "ownershipPoints": 0, "circuitPoints": 0, "egNavigationPoints": 0, "autoPoints": 0, "dcPoints": 0, "endgamePoints": 0, "penaltyPointsCommitted": 0, "prePenaltyTotal": 0, "autoJunctionCones": [0, 0, 0, 0], "dcJunctionCones": [0, 0, 0, 0], "beacons": 0, "ownedJunctions": 0, "circuit": false, "totalPoints": 0}, {"alliance": "Red", "team": 0, "sideOfField": "SCORING_SIDE", "initSignalSleeve1": false, "initSignalSleeve2": false, "robot1Auto": "NONE", "robot2Auto": "NONE", "autoTerminal": 0, "autoJunctions": [[[], [], [], [], []], [[], [], [], [], []], [[], [], [], [], []], [[], [], [], [], []], [[], [], [], [], []]], "dcJunctions": [[[], [], [], [], []], [[], [], [], [], []], [[], [], [], [], []], [[], [], [], [], []], [[], [], [], [], []]], "dcTerminalNear": 1, "dcTerminalFar": 0, "egNavigated1": true, "egNavigated2": true, "minorPenalties": 0, "majorPenalties": 0, "autoNavigationPoints": 0, "signalBonusPoints": 0, "autoJunctionConePoints": 0, "autoTerminalConePoints": 0, "dcJunctionConePoints": 0, "dcTerminalConePoints": 1, "ownershipPoints": 0, "circuitPoints": 0, "egNavigationPoints": 4, "autoPoints": 0, "dcPoints": 1, "endgamePoints": 4, "penaltyPointsCommitted": 0, "prePenaltyTotal": 5, "autoJunctionCones": [0, 0, 0, 0], "dcJunctionCones": [0, 0, 0, 0], "beacons": 0, "ownedJunctions": 0, "circuit": false, "totalPoints": 5}]}, {"matchLevel": "QUALIFICATION", "matchSeries": 0, "matchNumber": 3, "randomization": 5, "alliances": [{"alliance": "Blue", "team": 0, "sideOfField": "SCORING_SIDE", "initSignalSleeve1": false, "initSignalSleeve2": false, "robot1Auto": "NONE", "robot2Auto": "SUBSTATION_TERMINAL", "autoTerminal": 1, "autoJunctions": [[[], [], [], [], []], [[], [], [], [], []], [[], [], [], [], []], [[], [], [], [], []], [[], [], [], [], []]], "dcJunctions": [[["MY_CONE"], [], [], [], []], [["MY_CONE"], [], [], [], []], [["MY_CONE"], [], ["MY_CONE"], [], []], [[], [], [], [], []], [[], [], [], [], []]], "dcTerminalNear": 3, "dcTerminalFar": 0, "egNavigated1": false, "egNavigated2": false, "minorPenalties": 0, "majorPenalties": 0, "autoNavigationPoints": 2, "signalBonusPoints": 0, "autoJunctionConePoints": 0, "autoTerminalConePoints": 1, "dcJunctionConePoints": 9, "dcTerminalConePoints": 3, "ownershipPoints": 12, "circuitPoints": 0, "egNavigationPoints": 0, "autoPoints": 3, "dcPoints": 12, "endgamePoints": 12, "penaltyPointsCommitted": 0, "prePenaltyTotal": 27, "autoJunctionCones": [0, 0, 0, 0], "dcJunctionCones": [3, 1, 0, 0], "beacons": 0, "ownedJunctions": 4, "circuit": false, "totalPoints": 27}, {"alliance": "Red", "team": 0, "sideOfField": "SCORING_SIDE", "initSignalSleeve1": false, "initSignalSleeve2": false, "robot1Auto": "NONE", "robot2Auto": "NONE", "autoTerminal": 0, "autoJunctions": [[[], [], [], [], []], [[], [], [], [], []], [[], [], [], [], []], [[], [], [], [], []], [[], [], [], [], []]], "dcJunctions": [[["OTHER_CONE"], [], [], [], []], [["OTHER_CONE"], [], [], [], []], [["OTHER_CONE"], [], ["OTHER_CONE"], [], []], [[], [], [], [], []], [[], [], [], [], []]], "dcTerminalNear": 3, "dcTerminalFar": 0, "egNavigated1": true, "egNavigated2": true, "minorPenalties": 0, "majorPenalties": 0, "autoNavigationPoints": 0, "signalBonusPoints": 0, "autoJunctionConePoints": 0, "autoTerminalConePoints": 0, "dcJunctionConePoints": 0, "dcTerminalConePoints": 3, "ownershipPoints": 0, "circuitPoints": 0, "egNavigationPoints": 4, "autoPoints": 0, "dcPoints": 3, "endgamePoints": 4, "penaltyPointsCommitted": 0, "prePenaltyTotal": 7, "autoJunctionCones": [0, 0, 0, 0], "dcJunctionCones": [0, 0, 0, 0], "beacons": 0, "ownedJunctions": 0, "circuit": false, "totalPoints": 7}]}, {"matchLevel": "QUALIFICATION", "matchSeries": 0, "matchNumber": 4, "randomization": 1, "alliances": [{"alliance": "Blue", "team": 0, "sideOfField": "SCORING_SIDE", "initSignalSleeve1": false, "initSignalSleeve2": false, "robot1Auto": "NONE", "robot2Auto": "SUBSTATION_TERMINAL", "autoTerminal": 1, "autoJunctions": [[[], [], [], [], []], [[], [], [], [], []], [[], [], [], [], []], [[], [], [], [], []], [[], [], [], [], []]], "dcJunctions": [[[], [], [], ["OTHER_CONE"], []], [[], [], [], [], ["OTHER_CONE", "OTHER_CONE", "OTHER_CONE"]], [[], [], [], [], []], [[], ["MY_CONE", "MY_CONE", "MY_CONE"], [], [], ["OTHER_CONE"]], [[], [], [], [], ["OTHER_CONE"]]], "dcTerminalNear": 1, "dcTerminalFar": 0, "egNavigated1": false, "egNavigated2": true, "minorPenalties": 0, "majorPenalties": 0, "autoNavigationPoints": 2, "signalBonusPoints": 0, "autoJunctionConePoints": 0, "autoTerminalConePoints": 1, "dcJunctionConePoints": 12, "dcTerminalConePoints": 1, "ownershipPoints": 3, "circuitPoints": 0, "egNavigationPoints": 2, "autoPoints": 3, "dcPoints": 13, "endgamePoints": 5, "penaltyPointsCommitted": 0, "prePenaltyTotal": 21, "autoJunctionCones": [0, 0, 0, 0], "dcJunctionCones": [0, 0, 3, 0], "beacons": 0, "ownedJunctions": 1, "circuit": false, "totalPoints": 21}, {"alliance": "Red", "team": 0, "sideOfField": "SCORING_SIDE", "initSignalSleeve1": false, "initSignalSleeve2": false, "robot1Auto": "NONE", "robot2Auto": "NONE", "autoTerminal": 0, "autoJunctions": [[[], [], [], [], []], [[], [], [], [], []], [[], [], [], [], []], [[], [], [], [], []], [[], [], [], [], []]], "dcJunctions": [[[], [], [], ["MY_CONE"], []], [[], [], [], [], ["MY_CONE", "MY_CONE", "MY_CONE"]], [[], [], [], [], []], [[], ["OTHER_CONE", "OTHER_CONE", "OTHER_CONE"], [], [], ["MY_CONE"]], [[], [], [], [], ["MY_CONE"]]], "dcTerminalNear": 0, "dcTerminalFar": 0, "egNavigated1": true, "egNavigated2": true, "minorPenalties": 0, "majorPenalties": 0, "autoNavigationPoints": 0, "signalBonusPoints": 0, "autoJunctionConePoints": 0, "autoTerminalConePoints": 0, "dcJunctionConePoints": 17, "dcTerminalConePoints": 0, "ownershipPoints": 12, "circuitPoints": 0, "egNavigationPoints": 4, "autoPoints": 0, "dcPoints": 17, "endgamePoints": 16, "penaltyPointsCommitted": 0, "prePenaltyTotal": 33, "autoJunctionCones": [0, 0, 0, 0], "dcJunctionCones": [1, 5, 0, 0], "beacons": 0, "ownedJunctions": 4, "circuit": false, "totalPoints": 33}]}, {"matchLevel": "QUALIFICATION", "matchSeries": 0, "matchNumber": 5, "randomization": 5, "alliances": [{"alliance": "Blue", "team": 0, "sideOfField": "SCORING_SIDE", "initSignalSleeve1": false, "initSignalSleeve2": false, "robot1Auto": "NONE", "robot2Auto": "NONE", "autoTerminal": 0, "autoJunctions": [[[], [], [], [], []], [[], [], [], [], []], [[], [], [], [], []], [[], [], [], [], []], [[], [], [], [], []]], "dcJunctions": [[[], [], [], [], []], [[], [], [], [], []], [[], [], [], [], []], [[], [], [], [], []], [[], [], [], [], ["OTHER_CONE"]]], "dcTerminalNear": 4, "dcTerminalFar": 0, "egNavigated1": true, "egNavigated2": true, "minorPenalties": 0, "majorPenalties": 0, "autoNavigationPoints": 0, "signalBonusPoints": 0, "autoJunctionConePoints": 0, "autoTerminalConePoints": 0, "dcJunctionConePoints": 0, "dcTerminalConePoints": 4, "ownershipPoints": 0, "circuitPoints": 0, "egNavigationPoints": 4, "autoPoints": 0, "dcPoints": 4, "endgamePoints": 4, "penaltyPointsCommitted": 0, "prePenaltyTotal": 8, "autoJunctionCones": [0, 0, 0, 0], "dcJunctionCones": [0, 0, 0, 0], "beacons": 0, "ownedJunctions": 0, "circuit": false, "totalPoints": 8}, {"alliance": "Red", "team": 0, "sideOfField": "SCORING_SIDE", "initSignalSleeve1": true, "initSignalSleeve2": false, "robot1Auto": "NONE", "robot2Auto": "NONE", "autoTerminal": 0, "autoJunctions": [[[], [], [], [], []], [[], [], [], [], []], [[], [], [], [], []], [[], [], [], [], []], [[], [], [], [], []]], "dcJunctions": [[[], [], [], [], []], [[], [], [], [], []], [[], [], [], [], []], [[], [], [], [], []], [[], [], [], [], ["MY_CONE"]]], "dcTerminalNear": 1, "dcTerminalFar": 0, "egNavigated1": true, "egNavigated2": false, "minorPenalties": 0, "majorPenalties": 0, "autoNavigationPoints": 0, "signalBonusPoints": 0, "autoJunctionConePoints": 0, "autoTerminalConePoints": 0, "dcJunctionConePoints": 2, "dcTerminalConePoints": 1, "ownershipPoints": 3, "circuitPoints": 0, "egNavigationPoints": 2, "autoPoints": 0, "dcPoints": 3, "endgamePoints": 5, "penaltyPointsCommitted": 0, "prePenaltyTotal": 8, "autoJunctionCones": [0, 0, 0, 0], "dcJunctionCones": [1, 0, 0, 0], "beacons": 0, "ownedJunctions": 1, "circuit": false, "totalPoints": 8}]}, {"matchLevel": "QUALIFICATION", "matchSeries": 0, "matchNumber": 6, "randomization": 3, "alliances": [{"alliance": "Blue", "team": 0, "sideOfField": "SCORING_SIDE", "initSignalSleeve1": true, "initSignalSleeve2": false, "robot1Auto": "SIGNAL_ZONE", "robot2Auto": "NONE", "autoTerminal": 0, "autoJunctions": [[[], [], [], [], []], [[], [], [], [], []], [[], [], [], [], []], [[], [], [], [], []], [[], [], [], [], []]], "dcJunctions": [[[], [], [], [], []], [[], ["MY_CONE", "MY_CONE", "MY_CONE", "MY_CONE", "MY_CONE", "MY_CONE"], [], [], ["OTHER_CONE"]], [[], [], [], [], []], [["MY_CONE", "MY_CONE", "MY_CONE"], [], [], [], []], [[], [], [], [], []]], "dcTerminalNear": 0, "dcTerminalFar": 0, "egNavigated1": false, "egNavigated2": true, "minorPenalties": 0, "majorPenalties": 0, "autoNavigationPoints": 0, "signalBonusPoints": 20, "autoJunctionConePoints": 0, "autoTerminalConePoints": 0, "dcJunctionConePoints": 33, "dcTerminalConePoints": 0, "ownershipPoints": 6, "circuitPoints": 0, "egNavigationPoints": 2, "autoPoints": 20, "dcPoints": 33, "endgamePoints": 8, "penaltyPointsCommitted": 0, "prePenaltyTotal": 61, "autoJunctionCones": [0, 0, 0, 0], "dcJunctionCones": [0, 3, 6, 0], "beacons": 0, "ownedJunctions": 2, "circuit": false, "totalPoints": 61}, {"alliance": "Red", "team": 0, "sideOfField": "SCORING_SIDE", "initSignalSleeve1": false, "initSignalSleeve2": false, "robot1Auto": "SUBSTATION_TERMINAL", "robot2Auto": "NONE", "autoTerminal": 0, "autoJunctions": [[[], [], [], [], []], [[], [], [], [], []], [[], [], [], [], []], [[], [], [], [], []], [[], [], [], [], []]], "dcJunctions": [[[], [], [], [], []], [[], ["OTHER_CONE", "OTHER_CONE", "OTHER_CONE", "OTHER_CONE", "OTHER_CONE", "OTHER_CONE"], [], [], ["MY_CONE"]], [[], [], [], [], []], [["OTHER_CONE", "OTHER_CONE", "OTHER_CONE"], [], [], [], []], [[], [], [], [], []]], "dcTerminalNear": 6, "dcTerminalFar": 0, "egNavigated1": true, "egNavigated2": true, "minorPenalties": 0, "majorPenalties": 0, "autoNavigationPoints": 2, "signalBonusPoints": 0, "autoJunctionConePoints": 0, "autoTerminalConePoints": 0, "dcJunctionConePoints": 3, "dcTerminalConePoints": 6, "ownershipPoints": 3, "circuitPoints": 0, "egNavigationPoints": 4, "autoPoints": 2, "dcPoints": 9, "endgamePoints": 7, "penaltyPointsCommitted": 0, "prePenaltyTotal": 18, "autoJunctionCones": [0, 0, 0, 0], "dcJunctionCones": [0, 1, 0, 0], "beacons": 0, "ownedJunctions": 1, "circuit": false, "totalPoints": 18}]}, {"matchLevel": "QUALIFICATION", "matchSeries": 0, "matchNumber": 7, "randomization": 6, "alliances": [{"alliance": "Blue", "team": 0, "sideOfField": "SCORING_SIDE", "initSignalSleeve1": false, "initSignalSleeve2": false, "robot1Auto": "SUBSTATION_TERMINAL", "robot2Auto": "NONE", "autoTerminal": 0, "autoJunctions": [[[], [], [], [], []], [[], [], [], [], []], [[], [], [], [], []], [[], [], [], [], []], [[], [], [], [], []]], "dcJunctions": [[[], [], [], [], []], [[], [], [], [], ["OTHER_CONE"]], [[], [], [], [], []], [[], [], [], [], []], [["MY_CONE"], [], [], [], []]], "dcTerminalNear": 7, "dcTerminalFar": 0, "egNavigated1": true, "egNavigated2": true, "minorPenalties": 0, "majorPenalties": 0, "autoNavigationPoints": 2, "signalBonusPoints": 0, "autoJunctionConePoints": 0, "autoTerminalConePoints": 0, "dcJunctionConePoints": 2, "dcTerminalConePoints": 7, "ownershipPoints": 3, "circuitPoints": 0, "egNavigationPoints": 4, "autoPoints": 2, "dcPoints": 9, "endgamePoints": 7, "penaltyPointsCommitted": 0, "prePenaltyTotal": 18, "autoJunctionCones": [0, 0, 0, 0], "dcJunctionCones": [1, 0, 0, 0], "beacons": 0, "ownedJunctions": 1, "circuit": false, "totalPoints": 18}, {"alliance": "Red", "team": 0, "sideOfField": "SCORING_SIDE", "initSignalSleeve1": false, "initSignalSleeve2": false, "robot1Auto": "NONE", "robot2Auto": "NONE", "autoTerminal": 0, "autoJunctions": [[[], [], [], [], []], [[], [], [], [], []], [[], [], [], [], []], [[], [], [], [], []], [[], [], [], [], []]], "dcJunctions": [[[], [], [], [], []], [[], [], [], [], ["MY_CONE"]], [[], [], [], [], []], [[], [], [], [], []], [["OTHER_CONE"], [], [], [], []]], "dcTerminalNear": 2, "dcTerminalFar": 0, "egNavigated1": true, "egNavigated2": true, "minorPenalties": 0, "majorPenalties": 0, "autoNavigationPoints": 0, "signalBonusPoints": 0, "autoJunctionConePoints": 0, "autoTerminalConePoints": 0, "dcJunctionConePoints": 3, "dcTerminalConePoints": 2, "ownershipPoints": 3, "circuitPoints": 0, "egNavigationPoints": 4, "autoPoints": 0, "dcPoints": 5, "endgamePoints": 7, "penaltyPointsCommitted": 0, "prePenaltyTotal": 12, "autoJunctionCones": [0, 0, 0, 0], "dcJunctionCones": [0, 1, 0, 0], "beacons": 0, "ownedJunctions": 1, "circuit": false, "totalPoints": 12}]}, {"matchLevel": "QUALIFICATION", "matchSeries": 0, "matchNumber": 8, "randomization": 2, "alliances": [{"alliance": "Blue", "team": 0, "sideOfField": "SCORING_SIDE", "initSignalSleeve1": false, "initSignalSleeve2": false, "robot1Auto": "NONE", "robot2Auto": "NONE", "autoTerminal": 0, "autoJunctions": [[[], [], [], [], []], [[], [], [], [], []], [[], [], [], [], []], [[], [], [], [], []], [[], [], [], [], []]], "dcJunctions": [[[], [], ["MY_CONE"], [], ["OTHER_CONE"]], [[], [], [], ["OTHER_CONE"], ["OTHER_CONE"]], [["MY_CONE"], [], ["MY_CONE"], ["OTHER_CONE"], ["OTHER_CONE"]], [[], [], [], [], []], [[], [], [], [], ["OTHER_CONE"]]], "dcTerminalNear": 1, "dcTerminalFar": 0, "egNavigated1": false, "egNavigated2": true, "minorPenalties": 0, "majorPenalties": 0, "autoNavigationPoints": 0, "signalBonusPoints": 0, "autoJunctionConePoints": 0, "autoTerminalConePoints": 0, "dcJunctionConePoints": 6, "dcTerminalConePoints": 1, "ownershipPoints": 9, "circuitPoints": 0, "egNavigationPoints": 2, "autoPoints": 0, "dcPoints": 7, "endgamePoints": 11, "penaltyPointsCommitted": 0, "prePenaltyTotal": 18, "autoJunctionCones": [0, 0, 0, 0], "dcJunctionCones": [3, 0, 0, 0], "beacons": 0, "ownedJunctions": 3, "circuit": false, "totalPoints": 18}, {"alliance": "Red", "team": 0, "sideOfField": "SCORING_SIDE", "initSignalSleeve1": false, "initSignalSleeve2": false, "robot1Auto": "NONE", "robot2Auto": "NONE", "autoTerminal": 0, "autoJunctions": [[[], [], [], [], []], [[], [], [], [], []], [[], [], [], [], []], [[], [], [], [], []], [[], [], [], [], []]], "dcJunctions": [[[], [], ["OTHER_CONE"], [], ["MY_CONE"]], [[], [], [], ["MY_CONE"], ["MY_CONE"]], [["OTHER_CONE"], [], ["OTHER_CONE"], ["MY_CONE"], ["MY_CONE"]], [[], [], [], [], []], [[], [], [], [], ["MY_CONE"]]], "dcTerminalNear": 2, "dcTerminalFar": 0, "egNavigated1": false, "egNavigated2": true, "minorPenalties": 0, "majorPenalties": 0, "autoNavigationPoints": 0, "signalBonusPoints": 0, "autoJunctionConePoints": 0, "autoTerminalConePoints": 0, "dcJunctionConePoints": 18, "dcTerminalConePoints": 2, "ownershipPoints": 18, "circuitPoints": 0, "egNavigationPoints": 2, "autoPoints": 0, "dcPoints": 20, "endgamePoints": 20, "penaltyPointsCommitted": 0, "prePenaltyTotal": 40, "autoJunctionCones": [0, 0, 0, 0], "dcJunctionCones": [3, 1, 1, 1], "beacons": 0, "ownedJunctions": 6, "circuit": false, "totalPoints": 40}]}, {"matchLevel": "QUALIFICATION", "matchSeries": 0, "matchNumber": 9, "randomization": 4, "alliances": [{"alliance": "Blue", "team": 0, "sideOfField": "SCORING_SIDE", "initSignalSleeve1": false, "initSignalSleeve2": false, "robot1Auto": "NONE", "robot2Auto": "NONE", "autoTerminal": 0, "autoJunctions": [[[], [], [], [], []], [[], [], [], [], []], [[], [], [], [], []], [[], [], [], [], []], [[], [], [], [], []]], "dcJunctions": [[[], [], [], [], []], [[], [], [], [], []], [[], [], [], [], ["OTHER_CONE"]], [["MY_CONE"], [], [], [], []], [[], [], [], [], []]], "dcTerminalNear": 1, "dcTerminalFar": 0, "egNavigated1": false, "egNavigated2": true, "minorPenalties": 0, "majorPenalties": 0, "autoNavigationPoints": 0, "signalBonusPoints": 0, "autoJunctionConePoints": 0, "autoTerminalConePoints": 0, "dcJunctionConePoints": 3, "dcTerminalConePoints": 1, "ownershipPoints": 3, "circuitPoints": 0, "egNavigationPoints": 2, "autoPoints": 0, "dcPoints": 4, "endgamePoints": 5, "penaltyPointsCommitted": 0, "prePenaltyTotal": 9, "autoJunctionCones": [0, 0, 0, 0], "dcJunctionCones": [0, 1, 0, 0], "beacons": 0, "ownedJunctions": 1, "circuit": false, "totalPoints": 9}, {"alliance": "Red", "team": 0, "sideOfField": "SCORING_SIDE", "initSignalSleeve1": false, "initSignalSleeve2": false, "robot1Auto": "NONE", "robot2Auto": "NONE", "autoTerminal": 0, "autoJunctions": [[[], [], [], [], []], [[], [], [], [], []], [[], [], [], [], []], [[], [], [], [], []], [[], [], [], [], []]], "dcJunctions": [[[], [], [], [], []], [[], [], [], [], []], [[], [], [], [], ["MY_CONE"]], [["OTHER_CONE"], [], [], [], []], [[], [], [], [], []]], "dcTerminalNear": 7, "dcTerminalFar": 1, "egNavigated1": true, "egNavigated2": true, "minorPenalties": 0, "majorPenalties": 0, "autoNavigationPoints": 0, "signalBonusPoints": 0, "autoJunctionConePoints": 0, "autoTerminalConePoints": 0, "dcJunctionConePoints": 2, "dcTerminalConePoints": 8, "ownershipPoints": 3, "circuitPoints": 0, "egNavigationPoints": 4, "autoPoints": 0, "dcPoints": 10, "endgamePoints": 7, "penaltyPointsCommitted": 0, "prePenaltyTotal": 17, "autoJunctionCones": [0, 0, 0, 0], "dcJunctionCones": [1, 0, 0, 0], "beacons": 0, "ownedJunctions": 1, "circuit": false, "totalPoints": 17}]}, {"matchLevel": "QUALIFICATION", "matchSeries": 0, "matchNumber": 10, "randomization": 6, "alliances": [{"alliance": "Blue", "team": 0, "sideOfField": "SCORING_SIDE", "initSignalSleeve1": false, "initSignalSleeve2": true, "robot1Auto": "NONE", "robot2Auto": "SIGNAL_ZONE", "autoTerminal": 0, "autoJunctions": [[[], [], [], [], []], [[], [], [], [], []], [[], [], [], [], []], [[], [], [], [], []], [[], [], [], [], []]], "dcJunctions": [[[], [], [], [], []], [[], ["MY_CONE", "MY_CONE", "MY_CONE", "MY_CONE", "MY_CONE"], [], [], []], [[], [], [], [], []], [[], [], [], [], []], [[], [], [], ["OTHER_CONE"], []]], "dcTerminalNear": 5, "dcTerminalFar": 0, "egNavigated1": true, "egNavigated2": false, "minorPenalties": 1, "majorPenalties": 0, "autoNavigationPoints": 0, "signalBonusPoints": 20, "autoJunctionConePoints": 0, "autoTerminalConePoints": 0, "dcJunctionConePoints": 20, "dcTerminalConePoints": 5, "ownershipPoints": 3, "circuitPoints": 0, "egNavigationPoints": 2, "autoPoints": 20, "dcPoints": 25, "endgamePoints": 5, "penaltyPointsCommitted": 10, "prePenaltyTotal": 50, "autoJunctionCones": [0, 0, 0, 0], "dcJunctionCones": [0, 0, 5, 0], "beacons": 0, "ownedJunctions": 1, "circuit": false, "totalPoints": 50}, {"alliance": "Red", "team": 0, "sideOfField": "SCORING_SIDE", "initSignalSleeve1": false, "initSignalSleeve2": false, "robot1Auto": "SUBSTATION_TERMINAL", "robot2Auto": "NONE", "autoTerminal": 0, "autoJunctions": [[[], [], [], [], []], [[], [], [], [], []], [[], [], [], [], []], [[], [], [], [], []], [[], [], [], [], []]], "dcJunctions": [[[], [], [], [], []], [[], ["OTHER_CONE", "OTHER_CONE", "OTHER_CONE", "OTHER_CONE", "OTHER_CONE"], [], [], []], [[], [], [], [], []], [[], [], [], [], []], [[], [], [], ["MY_CONE"], []]], "dcTerminalNear": 2, "dcTerminalFar": 0, "egNavigated1": true, "egNavigated2": true, "minorPenalties": 0, "majorPenalties": 0, "autoNavigationPoints": 2, "signalBonusPoints": 0, "autoJunctionConePoints": 0, "autoTerminalConePoints": 0, "dcJunctionConePoints": 3, "dcTerminalConePoints": 2, "ownershipPoints": 3, "circuitPoints": 0, "egNavigationPoints": 4, "autoPoints": 2, "dcPoints": 5, "endgamePoints": 7, "penaltyPointsCommitted": 0, "prePenaltyTotal": 14, "autoJunctionCones": [0, 0, 0, 0], "dcJunctionCones": [0, 1, 0, 0], "beacons": 0, "ownedJunctions": 1, "circuit": false, "totalPoints": 24}]}, {"matchLevel": "QUALIFICATION", "matchSeries": 0, "matchNumber": 11, "randomization": 6, "alliances": [{"alliance": "Blue", "team": 0, "sideOfField": "SCORING_SIDE", "initSignalSleeve1": false, "initSignalSleeve2": false, "robot1Auto": "NONE", "robot2Auto": "NONE", "autoTerminal": 0, "autoJunctions": [[[], [], [], [], []], [[], [], [], [], []], [[], [], [], [], []], [[], [], [], [], []], [[], [], [], [], []]], "dcJunctions": [[[], ["MY_CONE", "MY_CONE"], [], [], []], [["MY_CONE"], [], [], [], []], [["MY_CONE"], [], [], [], ["OTHER_CONE"]], [["MY_CONE"], [], [], [], []], [["MY_CONE"], [], [], [], []]], "dcTerminalNear": 0, "dcTerminalFar": 0, "egNavigated1": false, "egNavigated2": false, "minorPenalties": 0, "majorPenalties": 0, "autoNavigationPoints": 0, "signalBonusPoints": 0, "autoJunctionConePoints": 0, "autoTerminalConePoints": 0, "dcJunctionConePoints": 16, "dcTerminalConePoints": 0, "ownershipPoints": 15, "circuitPoints": 0, "egNavigationPoints": 0, "autoPoints": 0, "dcPoints": 16, "endgamePoints": 15, "penaltyPointsCommitted": 0, "prePenaltyTotal": 31, "autoJunctionCones": [0, 0, 0, 0], "dcJunctionCones": [2, 4, 0, 0], "beacons": 0, "ownedJunctions": 5, "circuit": false, "totalPoints": 31}, {"alliance": "Red", "team": 0, "sideOfField": "SCORING_SIDE", "initSignalSleeve1": false, "initSignalSleeve2": true, "robot1Auto": "SUBSTATION_TERMINAL", "robot2Auto": "NONE", "autoTerminal": 0, "autoJunctions": [[[], [], [], [], []], [[], [], [], [], []], [[], [], [], [], []], [[], [], [], [], []], [[], [], [], [], []]], "dcJunctions": [[[], ["OTHER_CONE", "OTHER_CONE"], [], [], []], [["OTHER_CONE"], [], [], [], []], [["OTHER_CONE"], [], [], [], ["MY_CONE"]], [["OTHER_CONE"], [], [], [], []], [["OTHER_CONE"], [], [], [], []]], "dcTerminalNear": 9, "dcTerminalFar": 0, "egNavigated1": true, "egNavigated2": false, "minorPenalties": 0, "majorPenalties": 0, "autoNavigationPoints": 2, "signalBonusPoints": 0, "autoJunctionConePoints": 0, "autoTerminalConePoints": 0, "dcJunctionConePoints": 2, "dcTerminalConePoints": 9, "ownershipPoints": 3, "circuitPoints": 0, "egNavigationPoints": 2, "autoPoints": 2, "dcPoints": 11, "endgamePoints": 5, "penaltyPointsCommitted": 0, "prePenaltyTotal": 18, "autoJunctionCones": [0, 0, 0, 0], "dcJunctionCones": [1, 0, 0, 0], "beacons": 0, "ownedJunctions": 1, "circuit": false, "totalPoints": 18}]}, {"matchLevel": "QUALIFICATION", "matchSeries": 0, "matchNumber": 12, "randomization": 3, "alliances": [{"alliance": "Blue", "team": 0, "sideOfField": "SCORING_SIDE", "initSignalSleeve1": false, "initSignalSleeve2": false, "robot1Auto": "NONE", "robot2Auto": "SUBSTATION_TERMINAL", "autoTerminal": 1, "autoJunctions": [[[], [], [], [], []], [[], [], [], [], []], [[], [], [], [], []], [[], [], [], [], []], [[], [], [], [], []]], "dcJunctions": [[[], [], [], [], []], [["MY_CONE"], [], [], [], []], [[], ["MY_CONE"], [], [], []], [[], ["MY_CONE"], [], [], []], [[], [], [], [], []]], "dcTerminalNear": 1, "dcTerminalFar": 0, "egNavigated1": false, "egNavigated2": true, "minorPenalties": 0, "majorPenalties": 0, "autoNavigationPoints": 2, "signalBonusPoints": 0, "autoJunctionConePoints": 0, "autoTerminalConePoints": 1, "dcJunctionConePoints": 12, "dcTerminalConePoints": 1, "ownershipPoints": 9, "circuitPoints": 0, "egNavigationPoints": 2, "autoPoints": 3, "dcPoints": 13, "endgamePoints": 11, "penaltyPointsCommitted": 0, "prePenaltyTotal": 27, "autoJunctionCones": [0, 0, 0, 0], "dcJunctionCones": [0, 1, 1, 1], "beacons": 0, "ownedJunctions": 3, "circuit": false, "totalPoints": 27}, {"alliance": "Red", "team": 0, "sideOfField": "SCORING_SIDE", "initSignalSleeve1": false, "initSignalSleeve2": false, "robot1Auto": "NONE", "robot2Auto": "SUBSTATION_TERMINAL", "autoTerminal": 0, "autoJunctions": [[[], [], [], [], []], [[], [], [], [], []], [[], [], [], [], []], [[], [], [], [], []], [[], [], [], [], []]], "dcJunctions": [[[], [], [], [], []], [["OTHER_CONE"], [], [], [], []], [[], ["OTHER_CONE"], [], [], []], [[], ["OTHER_CONE"], [], [], []], [[], [], [], [], []]], "dcTerminalNear": 1, "dcTerminalFar": 0, "egNavigated1": false, "egNavigated2": true, "minorPenalties": 0, "majorPenalties": 0, "autoNavigationPoints": 2, "signalBonusPoints": 0, "autoJunctionConePoints": 0, "autoTerminalConePoints": 0, "dcJunctionConePoints": 0, "dcTerminalConePoints": 1, "ownershipPoints": 0, "circuitPoints": 0, "egNavigationPoints": 2, "autoPoints": 2, "dcPoints": 1, "endgamePoints": 2, "penaltyPointsCommitted": 0, "prePenaltyTotal": 5, "autoJunctionCones": [0, 0, 0, 0], "dcJunctionCones": [0, 0, 0, 0], "beacons": 0, "ownedJunctions": 0, "circuit": false, "totalPoints": 5}]}, {"matchLevel": "QUALIFICATION", "matchSeries": 0, "matchNumber": 13, "randomization": 5, "alliances": [{"alliance": "Blue", "team": 0, "sideOfField": "SCORING_SIDE", "initSignalSleeve1": false, "initSignalSleeve2": false, "robot1Auto": "NONE", "robot2Auto": "NONE", "autoTerminal": 0, "autoJunctions": [[[], [], [], [], []], [[], [], [], [], []], [[], [], [], [], []], [[], [], [], [], []], [[], [], [], [], []]], "dcJunctions": [[["MY_CONE"], [], ["MY_CONE"], [], []], [[], [], [], [], ["OTHER_CONE"]], [["MY_CONE"], [], ["MY_CONE"], [], []], [[], [], [], [], []], [["MY_CONE"], [], [], [], []]], "dcTerminalNear": 1, "dcTerminalFar": 0, "egNavigated1": true, "egNavigated2": true, "minorPenalties": 0, "majorPenalties": 0, "autoNavigationPoints": 0, "signalBonusPoints": 0, "autoJunctionConePoints": 0, "autoTerminalConePoints": 0, "dcJunctionConePoints": 10, "dcTerminalConePoints": 1, "ownershipPoints": 15, "circuitPoints": 0, "egNavigationPoints": 4, "autoPoints": 0, "dcPoints": 11, "endgamePoints": 19, "penaltyPointsCommitted": 0, "prePenaltyTotal": 30, "autoJunctionCones": [0, 0, 0, 0], "dcJunctionCones": [5, 0, 0, 0], "beacons": 0, "ownedJunctions": 5, "circuit": false, "totalPoints": 40}, {"alliance": "Red", "team": 0, "sideOfField": "SCORING_SIDE", "initSignalSleeve1": false, "initSignalSleeve2": false, "robot1Auto": "SUBSTATION_TERMINAL", "robot2Auto": "NONE", "autoTerminal": 0, "autoJunctions": [[[], [], [], [], []], [[], [], [], [], []], [[], [], [], [], []], [[], [], [], [], []], [[], [], [], [], []]], "dcJunctions": [[["OTHER_CONE"], [], ["OTHER_CONE"], [], []], [[], [], [], [], ["MY_CONE"]], [["OTHER_CONE"], [], ["OTHER_CONE"], [], []], [[], [], [], [], []], [["OTHER_CONE"], [], [], [], []]], "dcTerminalNear": 8, "dcTerminalFar": 0, "egNavigated1": false, "egNavigated2": true, "minorPenalties": 1, "majorPenalties": 0, "autoNavigationPoints": 2, "signalBonusPoints": 0, "autoJunctionConePoints": 0, "autoTerminalConePoints": 0, "dcJunctionConePoints": 3, "dcTerminalConePoints": 8, "ownershipPoints": 3, "circuitPoints": 0, "egNavigationPoints": 2, "autoPoints": 2, "dcPoints": 11, "endgamePoints": 5, "penaltyPointsCommitted": 10, "prePenaltyTotal": 18, "autoJunctionCones": [0, 0, 0, 0], "dcJunctionCones": [0, 1, 0, 0], "beacons": 0, "ownedJunctions": 1, "circuit": false, "totalPoints": 18}]}, {"matchLevel": "QUALIFICATION", "matchSeries": 0, "matchNumber": 14, "randomization": 5, "alliances": [{"alliance": "Blue", "team": 0, "sideOfField": "SCORING_SIDE", "initSignalSleeve1": false, "initSignalSleeve2": true, "robot1Auto": "NONE", "robot2Auto": "SIGNAL_ZONE", "autoTerminal": 0, "autoJunctions": [[[], [], [], [], []], [[], [], [], [], []], [[], [], [], [], []], [[], [], [], [], []], [[], [], [], [], []]], "dcJunctions": [[[], [], ["OTHER_CONE"], [], ["OTHER_CONE"]], [["MY_CONE"], ["MY_CONE"], [], [], []], [[], [], [], [], ["OTHER_CONE"]], [["MY_CONE"], ["MY_CONE"], [], [], []], [[], [], [], [], ["OTHER_CONE"]]], "dcTerminalNear": 0, "dcTerminalFar": 0, "egNavigated1": true, "egNavigated2": false, "minorPenalties": 0, "majorPenalties": 0, "autoNavigationPoints": 0, "signalBonusPoints": 20, "autoJunctionConePoints": 0, "autoTerminalConePoints": 0, "dcJunctionConePoints": 14, "dcTerminalConePoints": 0, "ownershipPoints": 12, "circuitPoints": 0, "egNavigationPoints": 2, "autoPoints": 20, "dcPoints": 14, "endgamePoints": 14, "penaltyPointsCommitted": 0, "prePenaltyTotal": 48, "autoJunctionCones": [0, 0, 0, 0], "dcJunctionCones": [0, 2, 2, 0], "beacons": 0, "ownedJunctions": 4, "circuit": false, "totalPoints": 68}, {"alliance": "Red", "team": 0, "sideOfField": "SCORING_SIDE", "initSignalSleeve1": false, "initSignalSleeve2": false, "robot1Auto": "NONE", "robot2Auto": "NONE", "autoTerminal": 0, "autoJunctions": [[[], [], [], [], []], [[], [], [], [], []], [[], [], [], [], []], [[], [], [], [], []], [[], [], [], [], []]], "dcJunctions": [[[], [], ["MY_CONE"], [], ["MY_CONE"]], [["OTHER_CONE"], ["OTHER_CONE"], [], [], []], [[], [], [], [], ["MY_CONE"]], [["OTHER_CONE"], ["OTHER_CONE"], [], [], []], [[], [], [], [], ["MY_CONE"]]], "dcTerminalNear": 5, "dcTerminalFar": 0, "egNavigated1": false, "egNavigated2": true, "minorPenalties": 2, "majorPenalties": 0, "autoNavigationPoints": 0, "signalBonusPoints": 0, "autoJunctionConePoints": 0, "autoTerminalConePoints": 0, "dcJunctionConePoints": 8, "dcTerminalConePoints": 5, "ownershipPoints": 12, "circuitPoints": 0, "egNavigationPoints": 2, "autoPoints": 0, "dcPoints": 13, "endgamePoints": 14, "penaltyPointsCommitted": 20, "prePenaltyTotal": 27, "autoJunctionCones": [0, 0, 0, 0], "dcJunctionCones": [4, 0, 0, 0], "beacons": 0, "ownedJunctions": 4, "circuit": false, "totalPoints": 27}]}, {"matchLevel": "QUALIFICATION", "matchSeries": 0, "matchNumber": 15, "randomization": 5, "alliances": [{"alliance": "Blue", "team": 0, "sideOfField": "SCORING_SIDE", "initSignalSleeve1": false, "initSignalSleeve2": false, "robot1Auto": "NONE", "robot2Auto": "SUBSTATION_TERMINAL", "autoTerminal": 0, "autoJunctions": [[[], [], [], [], []], [[], [], [], [], []], [[], [], [], [], []], [[], [], [], [], []], [[], [], [], [], []]], "dcJunctions": [[["MY_CONE"], [], [], [], ["OTHER_CONE"]], [[], [], [], [], []], [[], ["MY_CONE"], [], [], ["OTHER_CONE"]], [["MY_CONE"], ["MY_CONE"], [], [], []], [[], [], [], [], []]], "dcTerminalNear": 0, "dcTerminalFar": 0, "egNavigated1": true, "egNavigated2": true, "minorPenalties": 0, "majorPenalties": 0, "autoNavigationPoints": 2, "signalBonusPoints": 0, "autoJunctionConePoints": 0, "autoTerminalConePoints": 0, "dcJunctionConePoints": 14, "dcTerminalConePoints": 0, "ownershipPoints": 12, "circuitPoints": 0, "egNavigationPoints": 4, "autoPoints": 2, "dcPoints": 14, "endgamePoints": 16, "penaltyPointsCommitted": 0, "prePenaltyTotal": 32, "autoJunctionCones": [0, 0, 0, 0], "dcJunctionCones": [1, 1, 1, 1], "beacons": 0, "ownedJunctions": 4, "circuit": false, "totalPoints": 32}, {"alliance": "Red", "team": 0, "sideOfField": "SCORING_SIDE", "initSignalSleeve1": false, "initSignalSleeve2": false, "robot1Auto": "NONE", "robot2Auto": "SUBSTATION_TERMINAL", "autoTerminal": 1, "autoJunctions": [[[], [], [], [], []], [[], [], [], [], []], [[], [], [], [], []], [[], [], [], [], []], [[], [], [], [], []]], "dcJunctions": [[["OTHER_CONE"], [], [], [], ["MY_CONE"]], [[], [], [], [], []], [[], ["OTHER_CONE"], [], [], ["MY_CONE"]], [["OTHER_CONE"], ["OTHER_CONE"], [], [], []], [[], [], [], [], []]], "dcTerminalNear": 3, "dcTerminalFar": 0, "egNavigated1": true, "egNavigated2": false, "minorPenalties": 0, "majorPenalties": 0, "autoNavigationPoints": 2, "signalBonusPoints": 0, "autoJunctionConePoints": 0, "autoTerminalConePoints": 1, "dcJunctionConePoints": 4, "dcTerminalConePoints": 3, "ownershipPoints": 6, "circuitPoints": 0, "egNavigationPoints": 2, "autoPoints": 3, "dcPoints": 7, "endgamePoints": 8, "penaltyPointsCommitted": 0, "prePenaltyTotal": 18, "autoJunctionCones": [0, 0, 0, 0], "dcJunctionCones": [2, 0, 0, 0], "beacons": 0, "ownedJunctions": 2, "circuit": false, "totalPoints": 18}]}, {"matchLevel": "QUALIFICATION", "matchSeries": 0, "matchNumber": 16, "randomization": 3, "alliances": [{"alliance": "Blue", "team": 0, "sideOfField": "SCORING_SIDE", "initSignalSleeve1": false, "initSignalSleeve2": false, "robot1Auto": "NONE", "robot2Auto": "NONE", "autoTerminal": 0, "autoJunctions": [[[], [], [], [], []], [[], [], [], [], []], [[], [], [], [], []], [[], [], [], [], []], [[], [], [], [], []]], "dcJunctions": [[[], [], [], [], []], [[], [], [], [], []], [[], [], [], [], []], [["MY_CONE", "MY_CONE"], [], [], ["OTHER_CONE", "OTHER_CONE", "OTHER_CONE", "OTHER_CONE", "OTHER_CONE", "OTHER_R1_BEACON"], []], [[], [], [], [], []]], "dcTerminalNear": 0, "dcTerminalFar": 0, "egNavigated1": false, "egNavigated2": true, "minorPenalties": 0, "majorPenalties": 0, "autoNavigationPoints": 0, "signalBonusPoints": 0, "autoJunctionConePoints": 0, "autoTerminalConePoints": 0, "dcJunctionConePoints": 6, "dcTerminalConePoints": 0, "ownershipPoints": 3, "circuitPoints": 0, "egNavigationPoints": 2, "autoPoints": 0, "dcPoints": 6, "endgamePoints": 5, "penaltyPointsCommitted": 0, "prePenaltyTotal": 11, "autoJunctionCones": [0, 0, 0, 0], "dcJunctionCones": [0, 2, 0, 0], "beacons": 0, "ownedJunctions": 1, "circuit": false, "totalPoints": 11}, {"alliance": "Red", "team": 0, "sideOfField": "SCORING_SIDE", "initSignalSleeve1": true, "initSignalSleeve2": false, "robot1Auto": "SIGNAL_ZONE", "robot2Auto": "NONE", "autoTerminal": 0, "autoJunctions": [[[], [], [], [], []], [[], [], [], [], []], [[], [], [], [], []], [[], [], [], [], []], [[], [], [], [], []]], "dcJunctions": [[[], [], [], [], []], [[], [], [], [], []], [[], [], [], [], []], [["OTHER_CONE", "OTHER_CONE"], [], [], ["MY_CONE", "MY_CONE", "MY_CONE", "MY_CONE", "MY_CONE", "MY_R1_BEACON"], []], [[], [], [], [], []]], "dcTerminalNear": 2, "dcTerminalFar": 1, "egNavigated1": true, "egNavigated2": true, "minorPenalties": 0, "majorPenalties": 0, "autoNavigationPoints": 0, "signalBonusPoints": 20, "autoJunctionConePoints": 0, "autoTerminalConePoints": 0, "dcJunctionConePoints": 20, "dcTerminalConePoints": 3, "ownershipPoints": 10, "circuitPoints": 0, "egNavigationPoints": 4, "autoPoints": 20, "dcPoints": 23, "endgamePoints": 14, "penaltyPointsCommitted": 0, "prePenaltyTotal": 57, "autoJunctionCones": [0, 0, 0, 0], "dcJunctionCones": [0, 0, 5, 0], "beacons": 1, "ownedJunctions": 1, "circuit": false, "totalPoints": 57}]}, {"matchLevel": "QUALIFICATION", "matchSeries": 0, "matchNumber": 17, "randomization": 1, "alliances": [{"alliance": "Blue", "team": 0, "sideOfField": "SCORING_SIDE", "initSignalSleeve1": false, "initSignalSleeve2": false, "robot1Auto": "NONE", "robot2Auto": "NONE", "autoTerminal": 0, "autoJunctions": [[[], [], [], [], []], [[], [], [], [], []], [[], [], [], [], []], [[], [], [], [], []], [[], [], [], [], []]], "dcJunctions": [[["MY_CONE"], [], ["MY_CONE"], [], []], [[], [], [], [], []], [["MY_CONE"], [], ["MY_CONE"], [], ["MY_CONE"]], [[], [], [], [], []], [["MY_CONE"], [], ["MY_CONE"], [], []]], "dcTerminalNear": 3, "dcTerminalFar": 0, "egNavigated1": true, "egNavigated2": true, "minorPenalties": 0, "majorPenalties": 0, "autoNavigationPoints": 0, "signalBonusPoints": 0, "autoJunctionConePoints": 0, "autoTerminalConePoints": 0, "dcJunctionConePoints": 14, "dcTerminalConePoints": 3, "ownershipPoints": 21, "circuitPoints": 0, "egNavigationPoints": 4, "autoPoints": 0, "dcPoints": 17, "endgamePoints": 25, "penaltyPointsCommitted": 0, "prePenaltyTotal": 42, "autoJunctionCones": [0, 0, 0, 0], "dcJunctionCones": [7, 0, 0, 0], "beacons": 0, "ownedJunctions": 7, "circuit": false, "totalPoints": 42}, {"alliance": "Red", "team": 0, "sideOfField": "SCORING_SIDE", "initSignalSleeve1": false, "initSignalSleeve2": false, "robot1Auto": "SUBSTATION_TERMINAL", "robot2Auto": "NONE", "autoTerminal": 0, "autoJunctions": [[[], [], [], [], []], [[], [], [], [], []], [[], [], [], [], []], [[], [], [], [], []], [[], [], [], [], []]], "dcJunctions": [[["OTHER_CONE"], [], ["OTHER_CONE"], [], []], [[], [], [], [], []], [["OTHER_CONE"], [], ["OTHER_CONE"], [], ["OTHER_CONE"]], [[], [], [], [], []], [["OTHER_CONE"], [], ["OTHER_CONE"], [], []]], "dcTerminalNear": 8, "dcTerminalFar": 0, "egNavigated1": true, "egNavigated2": false, "minorPenalties": 0, "majorPenalties": 0, "autoNavigationPoints": 2, "signalBonusPoints": 0, "autoJunctionConePoints": 0, "autoTerminalConePoints": 0, "dcJunctionConePoints": 0, "dcTerminalConePoints": 8, "ownershipPoints": 0, "circuitPoints": 0, "egNavigationPoints": 2, "autoPoints": 2, "dcPoints": 8, "endgamePoints": 2, "penaltyPointsCommitted": 0, "prePenaltyTotal": 12, "autoJunctionCones": [0, 0, 0, 0], "dcJunctionCones": [0, 0, 0, 0], "beacons": 0, "ownedJunctions": 0, "circuit": false, "totalPoints": 12}]}, {"matchLevel": "QUALIFICATION", "matchSeries": 0, "matchNumber": 18, "randomization": 3, "alliances": [{"alliance": "Blue", "team": 0, "sideOfField": "SCORING_SIDE", "initSignalSleeve1": false, "initSignalSleeve2": false, "robot1Auto": "NONE", "robot2Auto": "SUBSTATION_TERMINAL", "autoTerminal": 1, "autoJunctions": [[[], [], [], [], []], [[], [], [], [], []], [[], [], [], [], []], [[], [], [], [], []], [[], [], [], [], []]], "dcJunctions": [[[], [], [], [], []], [["MY_CONE", "MY_CONE"], ["MY_CONE"], [], [], []], [[], [], [], [], []], [["MY_CONE"], ["MY_CONE"], [], [], ["OTHER_CONE"]], [[], [], [], [], []]], "dcTerminalNear": 3, "dcTerminalFar": 0, "egNavigated1": true, "egNavigated2": true, "minorPenalties": 1, "majorPenalties": 0, "autoNavigationPoints": 2, "signalBonusPoints": 0, "autoJunctionConePoints": 0, "autoTerminalConePoints": 1, "dcJunctionConePoints": 17, "dcTerminalConePoints": 3, "ownershipPoints": 12, "circuitPoints": 0, "egNavigationPoints": 4, "autoPoints": 3, "dcPoints": 20, "endgamePoints": 16, "penaltyPointsCommitted": 10, "prePenaltyTotal": 39, "autoJunctionCones": [0, 0, 0, 0], "dcJunctionCones": [0, 3, 2, 0], "beacons": 0, "ownedJunctions": 4, "circuit": false, "totalPoints": 59}, {"alliance": "Red", "team": 0, "sideOfField": "SCORING_SIDE", "initSignalSleeve1": false, "initSignalSleeve2": false, "robot1Auto": "NONE", "robot2Auto": "NONE", "autoTerminal": 0, "autoJunctions": [[[], [], [], [], []], [[], [], [], [], []], [[], [], [], [], []], [[], [], [], [], []], [[], [], [], [], []]], "dcJunctions": [[[], [], [], [], []], [["OTHER_CONE", "OTHER_CONE"], ["OTHER_CONE"], [], [], []], [[], [], [], [], []], [["OTHER_CONE"], ["OTHER_CONE"], [], [], ["MY_CONE"]], [[], [], [], [], []]], "dcTerminalNear": 0, "dcTerminalFar": 0, "egNavigated1": false, "egNavigated2": false, "minorPenalties": 2, "majorPenalties": 0, "autoNavigationPoints": 0, "signalBonusPoints": 0, "autoJunctionConePoints": 0, "autoTerminalConePoints": 0, "dcJunctionConePoints": 3, "dcTerminalConePoints": 0, "ownershipPoints": 3, "circuitPoints": 0, "egNavigationPoints": 0, "autoPoints": 0, "dcPoints": 3, "endgamePoints": 3, "penaltyPointsCommitted": 20, "prePenaltyTotal": 6, "autoJunctionCones": [0, 0, 0, 0], "dcJunctionCones": [0, 1, 0, 0], "beacons": 0, "ownedJunctions": 1, "circuit": false, "totalPoints": 16}]}, {"matchLevel": "QUALIFICATION", "matchSeries": 0, "matchNumber": 19, "randomization": 6, "alliances": [{"alliance": "Blue", "team": 0, "sideOfField": "SCORING_SIDE", "initSignalSleeve1": false, "initSignalSleeve2": false, "robot1Auto": "NONE", "robot2Auto": "NONE", "autoTerminal": 0, "autoJunctions": [[[], [], [], [], []], [[], [], [], [], []], [[], [], [], [], []], [[], [], [], [], []], [[], [], [], [], ["OTHER_CONE"]]], "dcJunctions": [[[], [], [], [], []], [["MY_CONE"], [], [], [], []], [[], [], ["OTHER_CONE"], [], ["OTHER_CONE"]], [[], [], [], [], []], [[], [], [], ["OTHER_CONE"], ["OTHER_CONE"]]], "dcTerminalNear": 3, "dcTerminalFar": 0, "egNavigated1": true, "egNavigated2": true, "minorPenalties": 1, "majorPenalties": 0, "autoNavigationPoints": 0, "signalBonusPoints": 0, "autoJunctionConePoints": 0, "autoTerminalConePoints": 0, "dcJunctionConePoints": 3, "dcTerminalConePoints": 3, "ownershipPoints": 3, "circuitPoints": 0, "egNavigationPoints": 4, "autoPoints": 0, "dcPoints": 6, "endgamePoints": 7, "penaltyPointsCommitted": 10, "prePenaltyTotal": 13, "autoJunctionCones": [0, 0, 0, 0], "dcJunctionCones": [0, 1, 0, 0], "beacons": 0, "ownedJunctions": 1, "circuit": false, "totalPoints": 13}, {"alliance": "Red", "team": 0, "sideOfField": "SCORING_SIDE", "initSignalSleeve1": true, "initSignalSleeve2": false, "robot1Auto": "NONE", "robot2Auto": "SUBSTATION_TERMINAL", "autoTerminal": 0, "autoJunctions": [[[], [], [], [], []], [[], [], [], [], []], [[], [], [], [], []], [[], [], [], [], []], [[], [], [], [], ["MY_CONE"]]], "dcJunctions": [[[], [], [], [], []], [["OTHER_CONE"], [], [], [], []], [[], [], ["MY_CONE"], [], ["MY_CONE"]], [[], [], [], [], []], [[], [], [], ["MY_CONE"], ["MY_CONE"]]], "dcTerminalNear": 0, "dcTerminalFar": 0, "egNavigated1": false, "egNavigated2": true, "minorPenalties": 0, "majorPenalties": 0, "autoNavigationPoints": 2, "signalBonusPoints": 0, "autoJunctionConePoints": 2, "autoTerminalConePoints": 0, "dcJunctionConePoints": 9, "dcTerminalConePoints": 0, "ownershipPoints": 12, "circuitPoints": 0, "egNavigationPoints": 2, "autoPoints": 4, "dcPoints": 9, "endgamePoints": 14, "penaltyPointsCommitted": 0, "prePenaltyTotal": 27, "autoJunctionCones": [1, 0, 0, 0], "dcJunctionCones": [3, 1, 0, 0], "beacons": 0, "ownedJunctions": 4, "circuit": false, "totalPoints": 37}]}, {"matchLevel": "QUALIFICATION", "matchSeries": 0, "matchNumber": 20, "randomization": 3, "alliances": [{"alliance": "Blue", "team": 0, "sideOfField": "SCORING_SIDE", "initSignalSleeve1": false, "initSignalSleeve2": false, "robot1Auto": "NONE", "robot2Auto": "NONE", "autoTerminal": 0, "autoJunctions": [[[], [], [], [], []], [[], [], [], [], []], [[], [], [], [], []], [[], [], [], [], []], [[], [], [], [], []]], "dcJunctions": [[["MY_CONE"], [], [], [], []], [[], [], [], ["OTHER_CONE"], []], [[], [], [], ["OTHER_CONE"], []], [[], [], [], ["OTHER_CONE", "OTHER_CONE", "OTHER_CONE"], ["OTHER_CONE"]], [["MY_CONE"], [], [], ["OTHER_CONE"], []]], "dcTerminalNear": 5, "dcTerminalFar": 0, "egNavigated1": true, "egNavigated2": true, "minorPenalties": 0, "majorPenalties": 0, "autoNavigationPoints": 0, "signalBonusPoints": 0, "autoJunctionConePoints": 0, "autoTerminalConePoints": 0, "dcJunctionConePoints": 4, "dcTerminalConePoints": 5, "ownershipPoints": 6, "circuitPoints": 0, "egNavigationPoints": 4, "autoPoints": 0, "dcPoints": 9, "endgamePoints": 10, "penaltyPointsCommitted": 0, "prePenaltyTotal": 19, "autoJunctionCones": [0, 0, 0, 0], "dcJunctionCones": [2, 0, 0, 0], "beacons": 0, "ownedJunctions": 2, "circuit": false, "totalPoints": 19}, {"alliance": "Red", "team": 0, "sideOfField": "SCORING_SIDE", "initSignalSleeve1": false, "initSignalSleeve2": true, "robot1Auto": "NONE", "robot2Auto": "SIGNAL_ZONE", "autoTerminal": 0, "autoJunctions": [[[], [], [], [], []], [[], [], [], [], []], [[], [], [], [], []], [[], [], [], [], []], [[], [], [], [], []]], "dcJunctions": [[["OTHER_CONE"], [], [], [], []], [[], [], [], ["MY_CONE"], []], [[], [], [], ["MY_CONE"], []], [[], [], [], ["MY_CONE", "MY_CONE", "MY_CONE"], ["MY_CONE"]], [["OTHER_CONE"], [], [], ["MY_CONE"], []]], "dcTerminalNear": 0, "dcTerminalFar": 0, "egNavigated1": false, "egNavigated2": false, "minorPenalties": 0, "majorPenalties": 0, "autoNavigationPoints": 0, "signalBonusPoints": 20, "autoJunctionConePoints": 0, "autoTerminalConePoints": 0, "dcJunctionConePoints": 27, "dcTerminalConePoints": 0, "ownershipPoints": 15, "circuitPoints": 0, "egNavigationPoints": 0, "autoPoints": 20, "dcPoints": 27, "endgamePoints": 15, "penaltyPointsCommitted": 0, "prePenaltyTotal": 62, "autoJunctionCones": [0, 0, 0, 0], "dcJunctionCones": [0, 2, 4, 1], "beacons": 0, "ownedJunctions": 5, "circuit": false, "totalPoints": 62}]}, {"matchLevel": "QUALIFICATION", "matchSeries": 0, "matchNumber": 21, "randomization": 4, "alliances": [{"alliance": "Blue", "team": 0, "sideOfField": "SCORING_SIDE", "initSignalSleeve1": false, "initSignalSleeve2": false, "robot1Auto": "NONE", "robot2Auto": "NONE", "autoTerminal": 0, "autoJunctions": [[[], [], [], [], []], [[], [], [], [], []], [[], [], [], [], []], [[], [], [], [], []], [[], [], [], [], []]], "dcJunctions": [[["MY_CONE"], [], ["MY_CONE"], [], ["MY_CONE"]], [[], [], [], [], ["OTHER_CONE", "OTHER_CONE", "OTHER_CONE"]], [["MY_CONE"], [], ["MY_CONE"], [], []], [["MY_CONE"], [], [], [], ["OTHER_CONE", "OTHER_CONE"]], [[], [], ["MY_CONE"], [], []]], "dcTerminalNear": 0, "dcTerminalFar": 0, "egNavigated1": true, "egNavigated2": false, "minorPenalties": 0, "majorPenalties": 0, "autoNavigationPoints": 0, "signalBonusPoints": 0, "autoJunctionConePoints": 0, "autoTerminalConePoints": 0, "dcJunctionConePoints": 15, "dcTerminalConePoints": 0, "ownershipPoints": 21, "circuitPoints": 0, "egNavigationPoints": 2, "autoPoints": 0, "dcPoints": 15, "endgamePoints": 23, "penaltyPointsCommitted": 0, "prePenaltyTotal": 38, "autoJunctionCones": [0, 0, 0, 0], "dcJunctionCones": [6, 1, 0, 0], "beacons": 0, "ownedJunctions": 7, "circuit": false, "totalPoints": 38}, {"alliance": "Red", "team": 0, "sideOfField": "SCORING_SIDE", "initSignalSleeve1": false, "initSignalSleeve2": false, "robot1Auto": "SUBSTATION_TERMINAL", "robot2Auto": "NONE", "autoTerminal": 1, "autoJunctions": [[[], [], [], [], []], [[], [], [], [], []], [[], [], [], [], []], [[], [], [], [], []], [[], [], [], [], []]], "dcJunctions": [[["OTHER_CONE"], [], ["OTHER_CONE"], [], ["OTHER_CONE"]], [[], [], [], [], ["MY_CONE", "MY_CONE", "MY_CONE"]], [["OTHER_CONE"], [], ["OTHER_CONE"], [], []], [["OTHER_CONE"], [], [], [], ["MY_CONE", "MY_CONE"]], [[], [], ["OTHER_CONE"], [], []]], "dcTerminalNear": 1, "dcTerminalFar": 0, "egNavigated1": true, "egNavigated2": true, "minorPenalties": 0, "majorPenalties": 0, "autoNavigationPoints": 2, "signalBonusPoints": 0, "autoJunctionConePoints": 0, "autoTerminalConePoints": 1, "dcJunctionConePoints": 15, "dcTerminalConePoints": 1, "ownershipPoints": 6, "circuitPoints": 0, "egNavigationPoints": 4, "autoPoints": 3, "dcPoints": 16, "endgamePoints": 10, "penaltyPointsCommitted": 0, "prePenaltyTotal": 29, "autoJunctionCones": [0, 0, 0, 0], "dcJunctionCones": [0, 5, 0, 0], "beacons": 0, "ownedJunctions": 2, "circuit": false, "totalPoints": 29}]}, {"matchLevel": "QUALIFICATION", "matchSeries": 0, "matchNumber": 22, "randomization": 3, "alliances": [{"alliance": "Blue", "team": 0, "sideOfField": "SCORING_SIDE", "initSignalSleeve1": false, "initSignalSleeve2": false, "robot1Auto": "NONE", "robot2Auto": "SUBSTATION_TERMINAL", "autoTerminal": 1, "autoJunctions": [[[], [], [], [], []], [[], [], [], [], []], [[], [], [], [], []], [[], [], [], [], []], [[], [], [], [], []]], "dcJunctions": [[[], [], [], ["OTHER_CONE"], []], [["MY_CONE"], [], [], [], ["OTHER_CONE"]], [[], [], [], [], ["OTHER_CONE"]], [[], [], [], [], ["OTHER_CONE"]], [[], [], [], ["OTHER_CONE"], ["OTHER_CONE"]]], "dcTerminalNear": 11, "dcTerminalFar": 0, "egNavigated1": false, "egNavigated2": true, "minorPenalties": 0, "majorPenalties": 0, "autoNavigationPoints": 2, "signalBonusPoints": 0, "autoJunctionConePoints": 0, "autoTerminalConePoints": 1, "dcJunctionConePoints": 3, "dcTerminalConePoints": 11, "ownershipPoints": 3, "circuitPoints": 0, "egNavigationPoints": 2, "autoPoints": 3, "dcPoints": 14, "endgamePoints": 5, "penaltyPointsCommitted": 0, "prePenaltyTotal": 22, "autoJunctionCones": [0, 0, 0, 0], "dcJunctionCones": [0, 1, 0, 0], "beacons": 0, "ownedJunctions": 1, "circuit": false, "totalPoints": 22}, {"alliance": "Red", "team": 0, "sideOfField": "SCORING_SIDE", "initSignalSleeve1": false, "initSignalSleeve2": false, "robot1Auto": "NONE", "robot2Auto": "NONE", "autoTerminal": 0, "autoJunctions": [[[], [], [], [], []], [[], [], [], [], []], [[], [], [], [], []], [[], [], [], [], []], [[], [], [], [], []]], "dcJunctions": [[[], [], [], ["MY_CONE"], []], [["OTHER_CONE"], [], [], [], ["MY_CONE"]], [[], [], [], [], ["MY_CONE"]], [[], [], [], [], ["MY_CONE"]], [[], [], [], ["MY_CONE"], ["MY_CONE"]]], "dcTerminalNear": 0, "dcTerminalFar": 1, "egNavigated1": true, "egNavigated2": false, "minorPenalties": 0, "majorPenalties": 0, "autoNavigationPoints": 0, "signalBonusPoints": 0, "autoJunctionConePoints": 0, "autoTerminalConePoints": 0, "dcJunctionConePoints": 16, "dcTerminalConePoints": 1, "ownershipPoints": 18, "circuitPoints": 0, "egNavigationPoints": 2, "autoPoints": 0, "dcPoints": 17, "endgamePoints": 20, "penaltyPointsCommitted": 0, "prePenaltyTotal": 37, "autoJunctionCones": [0, 0, 0, 0], "dcJunctionCones": [2, 4, 0, 0], "beacons": 0, "ownedJunctions": 6, "circuit": false, "totalPoints": 37}]}, {"matchLevel": "QUALIFICATION", "matchSeries": 0, "matchNumber": 23, "randomization": 6, "alliances": [{"alliance": "Blue", "team": 0, "sideOfField": "SCORING_SIDE", "initSignalSleeve1": false, "initSignalSleeve2": false, "robot1Auto": "NONE", "robot2Auto": "NONE", "autoTerminal": 0, "autoJunctions": [[[], [], [], [], []], [[], [], [], [], []], [[], [], [], [], []], [[], [], [], [], []], [[], [], [], [], []]], "dcJunctions": [[["MY_CONE"], [], [], [], []], [[], [], [], [], []], [["MY_CONE"], [], [], [], ["OTHER_CONE"]], [[], [], [], [], []], [[], [], [], [], ["OTHER_CONE"]]], "dcTerminalNear": 2, "dcTerminalFar": 0, "egNavigated1": false, "egNavigated2": true, "minorPenalties": 0, "majorPenalties": 0, "autoNavigationPoints": 0, "signalBonusPoints": 0, "autoJunctionConePoints": 0, "autoTerminalConePoints": 0, "dcJunctionConePoints": 4, "dcTerminalConePoints": 2, "ownershipPoints": 6, "circuitPoints": 0, "egNavigationPoints": 2, "autoPoints": 0, "dcPoints": 6, "endgamePoints": 8, "penaltyPointsCommitted": 0, "prePenaltyTotal": 14, "autoJunctionCones": [0, 0, 0, 0], "dcJunctionCones": [2, 0, 0, 0], "beacons": 0, "ownedJunctions": 2, "circuit": false, "totalPoints": 14}, {"alliance": "Red", "team": 0, "sideOfField": "SCORING_SIDE", "initSignalSleeve1": false, "initSignalSleeve2": false, "robot1Auto": "NONE", "robot2Auto": "SUBSTATION_TERMINAL", "autoTerminal": 0, "autoJunctions": [[[], [], [], [], []], [[], [], [], [], []], [[], [], [], [], []], [[], [], [], [], []], [[], [], [], [], []]], "dcJunctions": [[["OTHER_CONE"], [], [], [], []], [[], [], [], [], []], [["OTHER_CONE"], [], [], [], ["MY_CONE"]], [[], [], [], [], []], [[], [], [], [], ["MY_CONE"]]], "dcTerminalNear": 0, "dcTerminalFar": 0, "egNavigated1": false, "egNavigated2": true, "minorPenalties": 0, "majorPenalties": 0, "autoNavigationPoints": 2, "signalBonusPoints": 0, "autoJunctionConePoints": 0, "autoTerminalConePoints": 0, "dcJunctionConePoints": 4, "dcTerminalConePoints": 0, "ownershipPoints": 6, "circuitPoints": 0, "egNavigationPoints": 2, "autoPoints": 2, "dcPoints": 4, "endgamePoints": 8, "penaltyPointsCommitted": 0, "prePenaltyTotal": 14, "autoJunctionCones": [0, 0, 0, 0], "dcJunctionCones": [2, 0, 0, 0], "beacons": 0, "ownedJunctions": 2, "circuit": false, "totalPoints": 14}]}]}